[{"Vereador": " ADILSON AMADEU", "Tipo_de_Gasto": "INTERMEDIADO - CORREIOS", "Nome_Da_Empresa": "CAMARA MUNICIPAL DE S\u00c3O PAULO", "CNPJ": "50.176.288/0001-28", "Valor": "2.691,09", "Mes/Ano": "09/2018"}, {"Vereador": " ADILSON AMADEU", "Tipo_de_Gasto": "INTERMEDIADO - LOCA\u00c7\u00c3O DE VE\u00cdCULOS", "Nome_Da_Empresa": "CAMARA MUNICIPAL DE S\u00c3O PAULO", "CNPJ": "50.176.288/0001-28", "Valor": "2.148,45", "Mes/Ano": "09/2018"}, {"Vereador": " ADRIANA RAMALHO", "Tipo_de_Gasto": "ASSINATURA DE JORNAIS E REVISTAS", "Nome_Da_Empresa": "S.A O ESTADO DE S. PAULO", "CNPJ": "61.533.949/0001-41", "Valor": "89,90", "Mes/Ano": "09/2018"}, {"Vereador": " ADRIANA RAMALHO", "Tipo_de_Gasto": "COMBUSTIVEL", "Nome_Da_Empresa": "POSTO JENNER LTDA", "CNPJ": "61.699.179/0001-01", "Valor": "1.257,00", "Mes/Ano": "09/2018"}, {"Vereador": " ADRIANA RAMALHO", "Tipo_de_Gasto": "COMPOSI\u00c7\u00c3O/ARTE/DIAGRAMA\u00c7\u00c3O/PRODU\u00c7\u00c3O/IMPRESSAO GRAFICA", "Nome_Da_Empresa": "VISUAL ARTE COPIADORA EIRELLI - ME", "CNPJ": "13.058.505/0001-59", "Valor": "140,00", "Mes/Ano": "09/2018"}, {"Vereador": " ADRIANA RAMALHO", "Tipo_de_Gasto": "CONTRATA\u00c7AO DE PESSOA JURIDICA", "Nome_Da_Empresa": "LOCAWEB SERVI\u00c7OS DE INTERNET S.A.", "CNPJ": "02.351.877/0001-52", "Valor": "65,00", "Mes/Ano": "09/2018"}, {"Vereador": " ADRIANA RAMALHO", "Tipo_de_Gasto": "CONTRATA\u00c7AO DE PESSOA JURIDICA", "Nome_Da_Empresa": "FERNANDO IGNACIO VIEIRA -ME", "CNPJ": "08.779.025/0001-47", "Valor": "7.500,00", "Mes/Ano": "09/2018"}, {"Vereador": " ADRIANA RAMALHO", "Tipo_de_Gasto": "CONTRATA\u00c7AO DE PESSOA JURIDICA", "Nome_Da_Empresa": "CONDE e DELL ARINGA - DESENVOLVIMENTO DE SOFTWARES LTDA - EPP", "CNPJ": "09.613.772/0001-73", "Valor": "250,00", "Mes/Ano": "09/2018"}, {"Vereador": " ADRIANA RAMALHO", "Tipo_de_Gasto": "ELABORA\u00c7\u00c3O/MANUTEN\u00c7AO DE SITE/HOSPEDAGEM", "Nome_Da_Empresa": "ALEXSANDRO FERREIRA AUGUSTO", "CNPJ": "29.831.210/0001-03", "Valor": "4.000,00", "Mes/Ano": "09/2018"}, {"Vereador": " ADRIANA RAMALHO", "Tipo_de_Gasto": "EVENTOS/SEMINARIOS", "Nome_Da_Empresa": "VIVAGRAF COMERCIO DE PRODUTOS PROMOCIONAIS EIRELI", "CNPJ": "25.200.006/0001-33", "Valor": "260,00", "Mes/Ano": "09/2018"}, {"Vereador": " ADRIANA RAMALHO", "Tipo_de_Gasto": "INTERMEDIADO - CORREIOS", "Nome_Da_Empresa": "CAMARA MUNICIPAL DE S\u00c3O PAULO", "CNPJ": "50.176.288/0001-28", "Valor": "1.636,75", "Mes/Ano": "09/2018"}, {"Vereador": " ADRIANA RAMALHO", "Tipo_de_Gasto": "INTERMEDIADO - LOCA\u00c7\u00c3O DE VE\u00cdCULOS", "Nome_Da_Empresa": "CAMARA MUNICIPAL DE S\u00c3O PAULO", "CNPJ": "50.176.288/0001-28", "Valor": "2.148,45", "Mes/Ano": "09/2018"}, {"Vereador": " ADRIANA RAMALHO", "Tipo_de_Gasto": "LOCA\u00c7\u00c3O DE MOVEIS E EQUIPAMENTOS", "Nome_Da_Empresa": "ALOC LOCA\u00c7\u00c3O E COMERCIO DE EQUIPAMENTOS DE INFORM\u00c1TICA LTDA.", "CNPJ": "07.071.575/0001-44", "Valor": "1.969,00", "Mes/Ano": "09/2018"}, {"Vereador": " ADRIANA RAMALHO", "Tipo_de_Gasto": "MATERIAL DE ESCRITORIO E OUTROS MATERIAIS DE CONSUMO", "Nome_Da_Empresa": "CENTER PAPEIS COMERCIAL LTDA.", "CNPJ": "06.226.820/0001-82", "Valor": "1.059,75", "Mes/Ano": "09/2018"}, {"Vereador": " ADRIANA RAMALHO", "Tipo_de_Gasto": "PROVEDOR DE INTERNET", "Nome_Da_Empresa": "TELEFONICA BRASIL S/A", "CNPJ": "02.558.157/0001-62", "Valor": "101,28", "Mes/Ano": "09/2018"}, {"Vereador": " ADRIANA RAMALHO", "Tipo_de_Gasto": "TELEFONE MOVEL", "Nome_Da_Empresa": "TELEFONICA BRASIL S/A", "CNPJ": "02.558.157/0001-62", "Valor": "606,91", "Mes/Ano": "09/2018"}, {"Vereador": " ALESSANDRO GUEDES", "Tipo_de_Gasto": "COMBUSTIVEL", "Nome_Da_Empresa": "AUTO POSTO GRANERO LTDA.", "CNPJ": "05.468.615/0001-60", "Valor": "1.258,47", "Mes/Ano": "09/2018"}, {"Vereador": " ALESSANDRO GUEDES", "Tipo_de_Gasto": "COMPOSI\u00c7\u00c3O/ARTE/DIAGRAMA\u00c7\u00c3O/PRODU\u00c7\u00c3O/IMPRESSAO GRAFICA", "Nome_Da_Empresa": "GISLAINE ARAUJO DOS SANTOS", "CNPJ": "23.204.601/0001-11", "Valor": "1.500,00", "Mes/Ano": "09/2018"}, {"Vereador": " ALESSANDRO GUEDES", "Tipo_de_Gasto": "CONTRATA\u00c7AO DE PESSOA JURIDICA", "Nome_Da_Empresa": "WORK LINE SYSTEM INFORM\u00c1TICA LTDA", "CNPJ": "67.002.329/0001-62", "Valor": "970,00", "Mes/Ano": "09/2018"}, {"Vereador": " ALESSANDRO GUEDES", "Tipo_de_Gasto": "ELABORA\u00c7\u00c3O/MANUTEN\u00c7AO DE SITE/HOSPEDAGEM", "Nome_Da_Empresa": "JOAO P DIAS DE CARVALHO", "CNPJ": "26.282.559/0001-45", "Valor": "5.000,00", "Mes/Ano": "09/2018"}, {"Vereador": " ALESSANDRO GUEDES", "Tipo_de_Gasto": "INTERMEDIADO - CORREIOS", "Nome_Da_Empresa": "CAMARA MUNICIPAL DE S\u00c3O PAULO", "CNPJ": "50.176.288/0001-28", "Valor": "536,05", "Mes/Ano": "09/2018"}, {"Vereador": " ALESSANDRO GUEDES", "Tipo_de_Gasto": "INTERMEDIADO - LOCA\u00c7\u00c3O DE VE\u00cdCULOS", "Nome_Da_Empresa": "CAMARA MUNICIPAL DE S\u00c3O PAULO", "CNPJ": "50.176.288/0001-28", "Valor": "2.148,45", "Mes/Ano": "09/2018"}, {"Vereador": " ALESSANDRO GUEDES", "Tipo_de_Gasto": "LOCA\u00c7\u00c3O DE MOVEIS E EQUIPAMENTOS", "Nome_Da_Empresa": "ATTBRASIL TECNOLOGIA LOCA\u00c7\u00c3O E SOLU\u00c7\u00d5ES EM INFORMATICA LTDA EPP", "CNPJ": "22.392.165/0001-99", "Valor": "2.090,00", "Mes/Ano": "09/2018"}, {"Vereador": " ALESSANDRO GUEDES", "Tipo_de_Gasto": "MATERIAL DE ESCRITORIO E OUTROS MATERIAIS DE CONSUMO", "Nome_Da_Empresa": "CENTER PAPEIS COMERCIAL LTDA.", "CNPJ": "06.226.820/0001-82", "Valor": "1.579,60", "Mes/Ano": "09/2018"}, {"Vereador": " ALESSANDRO GUEDES", "Tipo_de_Gasto": "TELEFONE FIXO", "Nome_Da_Empresa": "TELEFONICA BRASIL S/A", "CNPJ": "02.558.157/0001-62", "Valor": "124,35", "Mes/Ano": "09/2018"}, {"Vereador": " ALESSANDRO GUEDES", "Tipo_de_Gasto": "TELEFONE MOVEL", "Nome_Da_Empresa": "NEXTEL TELECOMUNICA\u00c7\u00d5ES LTDA", "CNPJ": "66.970.229/0001-67", "Valor": "249,99", "Mes/Ano": "09/2018"}, {"Vereador": " ALFREDINHO", "Tipo_de_Gasto": "CONTRATA\u00c7AO DE PESSOA JURIDICA", "Nome_Da_Empresa": "TECNEGOCIOS SOLU\u00c7OES EM INFORMATICA LTDA- ME", "CNPJ": "11.521.613/0001-90", "Valor": "330,00", "Mes/Ano": "09/2018"}, {"Vereador": " ALFREDINHO", "Tipo_de_Gasto": "INTERMEDIADO - LOCA\u00c7\u00c3O DE VE\u00cdCULOS", "Nome_Da_Empresa": "CAMARA MUNICIPAL DE S\u00c3O PAULO", "CNPJ": "50.176.288/0001-28", "Valor": "2.148,45", "Mes/Ano": "09/2018"}, {"Vereador": " ALFREDINHO", "Tipo_de_Gasto": "LOCA\u00c7\u00c3O DE MOVEIS E EQUIPAMENTOS", "Nome_Da_Empresa": "ATTBRASIL TECNOLOGIA LOCA\u00c7\u00c3O E SOLU\u00c7\u00d5ES EM INFORMATICA LTDA EPP", "CNPJ": "22.392.165/0001-99", "Valor": "1.930,00", "Mes/Ano": "09/2018"}, {"Vereador": " ALFREDINHO", "Tipo_de_Gasto": "MATERIAL DE ESCRITORIO E OUTROS MATERIAIS DE CONSUMO", "Nome_Da_Empresa": "CENTER PAPEIS COMERCIAL LTDA.", "CNPJ": "06.226.820/0001-82", "Valor": "1.409,60", "Mes/Ano": "09/2018"}, {"Vereador": " AMAURI SILVA", "Tipo_de_Gasto": "COMBUSTIVEL", "Nome_Da_Empresa": "PORTAL LESTE AUTO POSTO LTDA", "CNPJ": "05.451.897/0001-93", "Valor": "776,89", "Mes/Ano": "09/2018"}, {"Vereador": " AMAURI SILVA", "Tipo_de_Gasto": "COMPOSI\u00c7\u00c3O/ARTE/DIAGRAMA\u00c7\u00c3O/PRODU\u00c7\u00c3O/IMPRESSAO GRAFICA", "Nome_Da_Empresa": "SANS\u00c3O BARBOZA DE LIMA ME", "CNPJ": "57.345.654/0001-74", "Valor": "7.200,00", "Mes/Ano": "09/2018"}, {"Vereador": " AMAURI SILVA", "Tipo_de_Gasto": "CONTRATA\u00c7AO DE PESSOA JURIDICA", "Nome_Da_Empresa": "SOLARYS SOLU\u00c7\u00d5ES DIGITAIS LTDA-ME", "CNPJ": "08.648.207/0001-89", "Valor": "700,00", "Mes/Ano": "09/2018"}, {"Vereador": " AMAURI SILVA", "Tipo_de_Gasto": "INTERMEDIADO - LOCA\u00c7\u00c3O DE VE\u00cdCULOS", "Nome_Da_Empresa": "CAMARA MUNICIPAL DE S\u00c3O PAULO", "CNPJ": "50.176.288/0001-28", "Valor": "2.148,45", "Mes/Ano": "09/2018"}, {"Vereador": " AMAURI SILVA", "Tipo_de_Gasto": "MATERIAL DE ESCRITORIO E OUTROS MATERIAIS DE CONSUMO", "Nome_Da_Empresa": "ROGERIO TEJEDA LISTE - EPP", "CNPJ": "13.579.523/0001-86", "Valor": "1.116,80", "Mes/Ano": "09/2018"}, {"Vereador": " ANDR\u00c9 SANTOS", "Tipo_de_Gasto": "ASSINATURA DE JORNAIS E REVISTAS", "Nome_Da_Empresa": "S.A O ESTADO DE S. PAULO", "CNPJ": "61.533.949/0001-41", "Valor": "68,90", "Mes/Ano": "09/2018"}, {"Vereador": " ANDR\u00c9 SANTOS", "Tipo_de_Gasto": "COMBUSTIVEL", "Nome_Da_Empresa": "AUTO POSTO GRANERO LTDA.", "CNPJ": "05.468.615/0001-60", "Valor": "1.018,19", "Mes/Ano": "09/2018"}, {"Vereador": " ANDR\u00c9 SANTOS", "Tipo_de_Gasto": "COMBUSTIVEL", "Nome_Da_Empresa": "AUTO POSTO PAES DE BARROS LTDA", "CNPJ": "61.800.777/0001-25", "Valor": "852,30", "Mes/Ano": "09/2018"}, {"Vereador": " ANDR\u00c9 SANTOS", "Tipo_de_Gasto": "INTERMEDIADO - LOCA\u00c7\u00c3O DE VE\u00cdCULOS", "Nome_Da_Empresa": "CAMARA MUNICIPAL DE S\u00c3O PAULO", "CNPJ": "50.176.288/0001-28", "Valor": "2.148,45", "Mes/Ano": "09/2018"}, {"Vereador": " ANDR\u00c9 SANTOS", "Tipo_de_Gasto": "LOCA\u00c7\u00c3O DE MOVEIS E EQUIPAMENTOS", "Nome_Da_Empresa": "WAVE INFORMATICA LTDA EPP", "CNPJ": "11.090.241/0001-95", "Valor": "610,00", "Mes/Ano": "09/2018"}, {"Vereador": " ANDR\u00c9 SANTOS", "Tipo_de_Gasto": "LOCA\u00c7\u00c3O DE MOVEIS E EQUIPAMENTOS", "Nome_Da_Empresa": "COMTI COMUNICA\u00c7\u00c3O E TECNOLOGIA LTDA ME", "CNPJ": "24.751.379/0001-30", "Valor": "3.175,00", "Mes/Ano": "09/2018"}, {"Vereador": " ANDR\u00c9 SANTOS", "Tipo_de_Gasto": "MATERIAL DE ESCRITORIO E OUTROS MATERIAIS DE CONSUMO", "Nome_Da_Empresa": "CENTER PAPEIS COMERCIAL LTDA.", "CNPJ": "06.226.820/0001-82", "Valor": "2.841,85", "Mes/Ano": "09/2018"}, {"Vereador": " ANDR\u00c9 SANTOS", "Tipo_de_Gasto": "TELEFONE FIXO", "Nome_Da_Empresa": "TELEFONICA BRASIL S/A", "CNPJ": "02.558.157/0001-62", "Valor": "171,22", "Mes/Ano": "09/2018"}, {"Vereador": " ANDR\u00c9 SANTOS", "Tipo_de_Gasto": "TELEFONE MOVEL", "Nome_Da_Empresa": "TELEFONICA BRASIL S/A", "CNPJ": "02.558.157/0001-62", "Valor": "389,99", "Mes/Ano": "09/2018"}, {"Vereador": " ARSELINO TATTO", "Tipo_de_Gasto": "ASSINATURA DE JORNAIS E REVISTAS", "Nome_Da_Empresa": "S.A O ESTADO DE S. PAULO", "CNPJ": "61.533.949/0001-41", "Valor": "104,90", "Mes/Ano": "09/2018"}, {"Vereador": " ARSELINO TATTO", "Tipo_de_Gasto": "COMBUSTIVEL", "Nome_Da_Empresa": "POSTO DE SERVI\u00c7OS ANTONIO PAES LTDA", "CNPJ": "62.409.305/0001-09", "Valor": "2.195,08", "Mes/Ano": "09/2018"}, {"Vereador": " ARSELINO TATTO", "Tipo_de_Gasto": "COMPOSI\u00c7\u00c3O/ARTE/DIAGRAMA\u00c7\u00c3O/PRODU\u00c7\u00c3O/IMPRESSAO GRAFICA", "Nome_Da_Empresa": "F\u00c1BRICA SETE GR\u00c1FICA E EDITORA LTDA - ME", "CNPJ": "00.651.238/0001-87", "Valor": "3.360,00", "Mes/Ano": "09/2018"}, {"Vereador": " ARSELINO TATTO", "Tipo_de_Gasto": "COMPOSI\u00c7\u00c3O/ARTE/DIAGRAMA\u00c7\u00c3O/PRODU\u00c7\u00c3O/IMPRESSAO GRAFICA", "Nome_Da_Empresa": "VISTAR PRESTA\u00c7\u00c3O DE SERVI\u00c7OS DE DIGITA\u00c7\u00c3O LTDA ME", "CNPJ": "08.689.647/0001-84", "Valor": "3.000,00", "Mes/Ano": "09/2018"}, {"Vereador": " ARSELINO TATTO", "Tipo_de_Gasto": "COMPOSI\u00c7\u00c3O/ARTE/DIAGRAMA\u00c7\u00c3O/PRODU\u00c7\u00c3O/IMPRESSAO GRAFICA", "Nome_Da_Empresa": "ANDRE COSTA DESIGNER -ME", "CNPJ": "13.554.502/0001-06", "Valor": "1.200,00", "Mes/Ano": "09/2018"}, {"Vereador": " ARSELINO TATTO", "Tipo_de_Gasto": "ELABORA\u00c7\u00c3O/MANUTEN\u00c7AO DE SITE/HOSPEDAGEM", "Nome_Da_Empresa": "VISTAR PRESTA\u00c7\u00c3O DE SERVI\u00c7OS DE DIGITA\u00c7\u00c3O LTDA ME", "CNPJ": "08.689.647/0001-84", "Valor": "2.500,00", "Mes/Ano": "09/2018"}, {"Vereador": " ARSELINO TATTO", "Tipo_de_Gasto": "INTERMEDIADO - CORREIOS", "Nome_Da_Empresa": "CAMARA MUNICIPAL DE S\u00c3O PAULO", "CNPJ": "50.176.288/0001-28", "Valor": "512,30", "Mes/Ano": "09/2018"}, {"Vereador": " ARSELINO TATTO", "Tipo_de_Gasto": "INTERMEDIADO - LOCA\u00c7\u00c3O DE VE\u00cdCULOS", "Nome_Da_Empresa": "CAMARA MUNICIPAL DE S\u00c3O PAULO", "CNPJ": "50.176.288/0001-28", "Valor": "2.148,45", "Mes/Ano": "09/2018"}, {"Vereador": " ARSELINO TATTO", "Tipo_de_Gasto": "LOCA\u00c7\u00c3O DE MOVEIS E EQUIPAMENTOS", "Nome_Da_Empresa": "SINALL COM E SERV DE M\u00c1QUINAS LTDA", "CNPJ": "69.064.053/0001-72", "Valor": "1.029,48", "Mes/Ano": "09/2018"}, {"Vereador": " ARSELINO TATTO", "Tipo_de_Gasto": "MATERIAL DE ESCRITORIO E OUTROS MATERIAIS DE CONSUMO", "Nome_Da_Empresa": "CENTER PAPEIS COMERCIAL LTDA.", "CNPJ": "06.226.820/0001-82", "Valor": "2.993,75", "Mes/Ano": "09/2018"}, {"Vereador": " ARSELINO TATTO", "Tipo_de_Gasto": "TELEFONE MOVEL", "Nome_Da_Empresa": "TELEFONICA BRASIL S/A", "CNPJ": "02.558.157/0001-62", "Valor": "127,73", "Mes/Ano": "09/2018"}, {"Vereador": " ATILIO FRANCISCO", "Tipo_de_Gasto": "COMBUSTIVEL", "Nome_Da_Empresa": "RIP POSTOS DE SERVI\u00c7O E COM LTDA", "CNPJ": "43.720.218/0001-23", "Valor": "1.174,69", "Mes/Ano": "09/2018"}, {"Vereador": " ATILIO FRANCISCO", "Tipo_de_Gasto": "COMPOSI\u00c7\u00c3O/ARTE/DIAGRAMA\u00c7\u00c3O/PRODU\u00c7\u00c3O/IMPRESSAO GRAFICA", "Nome_Da_Empresa": "IRISARA COM\u00c9RCIO E SERVI\u00c7OS LTDA.", "CNPJ": "10.376.277/0001-77", "Valor": "660,00", "Mes/Ano": "09/2018"}, {"Vereador": " ATILIO FRANCISCO", "Tipo_de_Gasto": "CONTRATA\u00c7AO DE PESSOA JURIDICA", "Nome_Da_Empresa": "ALEXANDER SANTANNA ANTONIO SERVI\u00c7OS E TECNOLOGIA - ME", "CNPJ": "07.983.427/0001-04", "Valor": "4.000,00", "Mes/Ano": "09/2018"}, {"Vereador": " ATILIO FRANCISCO", "Tipo_de_Gasto": "CONTRATA\u00c7AO DE PESSOA JURIDICA", "Nome_Da_Empresa": "STYLU FENIX PRODU\u00c7\u00d5ES AUDIOVISUAIS LTDA", "CNPJ": "11.263.684/0001-30", "Valor": "3.522,00", "Mes/Ano": "09/2018"}, {"Vereador": " ATILIO FRANCISCO", "Tipo_de_Gasto": "CONTRATA\u00c7AO DE PESSOA JURIDICA", "Nome_Da_Empresa": "MIRIAM ZIBORDI", "CNPJ": "30.244.087/0001-03", "Valor": "365,70", "Mes/Ano": "09/2018"}, {"Vereador": " ATILIO FRANCISCO", "Tipo_de_Gasto": "INTERMEDIADO - CORREIOS", "Nome_Da_Empresa": "CAMARA MUNICIPAL DE S\u00c3O PAULO", "CNPJ": "50.176.288/0001-28", "Valor": "1.027,26", "Mes/Ano": "09/2018"}, {"Vereador": " ATILIO FRANCISCO", "Tipo_de_Gasto": "INTERMEDIADO - LOCA\u00c7\u00c3O DE VE\u00cdCULOS", "Nome_Da_Empresa": "CAMARA MUNICIPAL DE S\u00c3O PAULO", "CNPJ": "50.176.288/0001-28", "Valor": "2.148,45", "Mes/Ano": "09/2018"}, {"Vereador": " ATILIO FRANCISCO", "Tipo_de_Gasto": "LIMPEZA DE VEICULOS", "Nome_Da_Empresa": "RIP POSTOS DE SERVI\u00c7O E COM LTDA", "CNPJ": "43.720.218/0001-23", "Valor": "150,00", "Mes/Ano": "09/2018"}, {"Vereador": " ATILIO FRANCISCO", "Tipo_de_Gasto": "LOCA\u00c7\u00c3O DE MOVEIS E EQUIPAMENTOS", "Nome_Da_Empresa": "K2G SUPRIMENTOS DE IMPRESS\u00c3O E INFORMATICA EIRELLI - ME", "CNPJ": "19.367.661/0001-88", "Valor": "200,00", "Mes/Ano": "09/2018"}, {"Vereador": " ATILIO FRANCISCO", "Tipo_de_Gasto": "MATERIAL DE ESCRITORIO E OUTROS MATERIAIS DE CONSUMO", "Nome_Da_Empresa": "CENTER PAPEIS COMERCIAL LTDA.", "CNPJ": "06.226.820/0001-82", "Valor": "2.833,55", "Mes/Ano": "09/2018"}, {"Vereador": " ATILIO FRANCISCO", "Tipo_de_Gasto": "TELEFONE FIXO", "Nome_Da_Empresa": "TELEFONICA BRASIL S/A", "CNPJ": "02.558.157/0001-62", "Valor": "165,53", "Mes/Ano": "09/2018"}, {"Vereador": " ATILIO FRANCISCO", "Tipo_de_Gasto": "TELEFONE MOVEL", "Nome_Da_Empresa": "NEXTEL TELECOMUNICA\u00c7\u00d5ES LTDA", "CNPJ": "66.970.229/0001-67", "Valor": "112,49", "Mes/Ano": "09/2018"}, {"Vereador": " AURELIO NOMURA", "Tipo_de_Gasto": "COMBUSTIVEL", "Nome_Da_Empresa": "POSTO PAISAGEM LTDA", "CNPJ": "60.895.653/0001-08", "Valor": "253,95", "Mes/Ano": "09/2018"}, {"Vereador": " AURELIO NOMURA", "Tipo_de_Gasto": "CONTRATA\u00c7AO DE PESSOA JURIDICA", "Nome_Da_Empresa": "FERNANDO NOBUTAKA TAKAHASHI", "CNPJ": "18.411.294/0001-00", "Valor": "3.890,00", "Mes/Ano": "09/2018"}, {"Vereador": " AURELIO NOMURA", "Tipo_de_Gasto": "INTERMEDIADO - CORREIOS", "Nome_Da_Empresa": "CAMARA MUNICIPAL DE S\u00c3O PAULO", "CNPJ": "50.176.288/0001-28", "Valor": "35,65", "Mes/Ano": "09/2018"}, {"Vereador": " AURELIO NOMURA", "Tipo_de_Gasto": "INTERMEDIADO - LOCA\u00c7\u00c3O DE VE\u00cdCULOS", "Nome_Da_Empresa": "CAMARA MUNICIPAL DE S\u00c3O PAULO", "CNPJ": "50.176.288/0001-28", "Valor": "2.148,45", "Mes/Ano": "09/2018"}, {"Vereador": " AURELIO NOMURA", "Tipo_de_Gasto": "LOCA\u00c7\u00c3O DE MOVEIS E EQUIPAMENTOS", "Nome_Da_Empresa": "COMAVI LOCA\u00c7\u00c3O E SERVI\u00c7OS EIRELLI EPP", "CNPJ": "17.303.742/0001-99", "Valor": "699,19", "Mes/Ano": "09/2018"}, {"Vereador": " AURELIO NOMURA", "Tipo_de_Gasto": "MATERIAL DE ESCRITORIO E OUTROS MATERIAIS DE CONSUMO", "Nome_Da_Empresa": "CENTER PAPEIS COMERCIAL LTDA.", "CNPJ": "06.226.820/0001-82", "Valor": "451,10", "Mes/Ano": "09/2018"}, {"Vereador": " CAIO MIRANDA", "Tipo_de_Gasto": "COMBUSTIVEL", "Nome_Da_Empresa": "AUTO POSTO NOVO CENTRO LTDA", "CNPJ": "02.646.144/0001-45", "Valor": "83,98", "Mes/Ano": "09/2018"}, {"Vereador": " CAIO MIRANDA", "Tipo_de_Gasto": "CONTRATA\u00c7AO DE PESSOA JURIDICA", "Nome_Da_Empresa": "UBA COMUNICACAO E PRODUCAO AUDIOVISUAL EIRELI", "CNPJ": "29.520.766/0001-89", "Valor": "7.500,00", "Mes/Ano": "09/2018"}, {"Vereador": " CAIO MIRANDA", "Tipo_de_Gasto": "INTERMEDIADO - CORREIOS", "Nome_Da_Empresa": "CAMARA MUNICIPAL DE S\u00c3O PAULO", "CNPJ": "50.176.288/0001-28", "Valor": "16,65", "Mes/Ano": "09/2018"}, {"Vereador": " CAIO MIRANDA", "Tipo_de_Gasto": "INTERMEDIADO - LOCA\u00c7\u00c3O DE VE\u00cdCULOS", "Nome_Da_Empresa": "CAMARA MUNICIPAL DE S\u00c3O PAULO", "CNPJ": "50.176.288/0001-28", "Valor": "2.148,45", "Mes/Ano": "09/2018"}, {"Vereador": " CAIO MIRANDA", "Tipo_de_Gasto": "MATERIAL DE ESCRITORIO E OUTROS MATERIAIS DE CONSUMO", "Nome_Da_Empresa": "K2G SUPRIMENTOS DE IMPRESS\u00c3O E INFORMATICA EIRELLI - ME", "CNPJ": "19.367.661/0001-88", "Valor": "608,70", "Mes/Ano": "09/2018"}, {"Vereador": " CAIO MIRANDA", "Tipo_de_Gasto": "REPROGRAFIA (XEROX/ENCADERNA\u00c7\u00c3O)", "Nome_Da_Empresa": "IRISARA COM\u00c9RCIO E SERVI\u00c7OS LTDA.", "CNPJ": "10.376.277/0001-77", "Valor": "114,00", "Mes/Ano": "09/2018"}, {"Vereador": " CAMILO CRIST\u00d3FARO", "Tipo_de_Gasto": "COMBUSTIVEL", "Nome_Da_Empresa": "TONICAR AUTO POSTO LTDA", "CNPJ": "61.990.750/0001-42", "Valor": "1.773,14", "Mes/Ano": "09/2018"}, {"Vereador": " CAMILO CRIST\u00d3FARO", "Tipo_de_Gasto": "COMPOSI\u00c7\u00c3O/ARTE/DIAGRAMA\u00c7\u00c3O/PRODU\u00c7\u00c3O/IMPRESSAO GRAFICA", "Nome_Da_Empresa": "MAJU GRAF GRAFICA LTDA ME", "CNPJ": "06.226.361/0001-37", "Valor": "6.070,00", "Mes/Ano": "09/2018"}, {"Vereador": " CAMILO CRIST\u00d3FARO", "Tipo_de_Gasto": "CONTRATA\u00c7AO DE PESSOA JURIDICA", "Nome_Da_Empresa": "INFORMATIX INFORMATICA LTDA ME", "CNPJ": "04.364.641/0001-86", "Valor": "2.500,00", "Mes/Ano": "09/2018"}, {"Vereador": " CAMILO CRIST\u00d3FARO", "Tipo_de_Gasto": "INTERMEDIADO - CORREIOS", "Nome_Da_Empresa": "CAMARA MUNICIPAL DE S\u00c3O PAULO", "CNPJ": "50.176.288/0001-28", "Valor": "557,45", "Mes/Ano": "09/2018"}, {"Vereador": " CAMILO CRIST\u00d3FARO", "Tipo_de_Gasto": "INTERMEDIADO - REPROGRAFIA (XEROX/ENCADERNA\u00c7\u00c3O)", "Nome_Da_Empresa": "CAMARA MUNICIPAL DE S\u00c3O PAULO", "CNPJ": "50.176.288/0001-28", "Valor": "15,54", "Mes/Ano": "09/2018"}, {"Vereador": " CAMILO CRIST\u00d3FARO", "Tipo_de_Gasto": "LOCA\u00c7\u00c3O DE MOVEIS E EQUIPAMENTOS", "Nome_Da_Empresa": "T.S. IMPORTS EIRELI - ME", "CNPJ": "23.017.310/0001-14", "Valor": "8.000,00", "Mes/Ano": "09/2018"}, {"Vereador": " CAMILO CRIST\u00d3FARO", "Tipo_de_Gasto": "MATERIAL DE ESCRITORIO E OUTROS MATERIAIS DE CONSUMO", "Nome_Da_Empresa": "CENTER PAPEIS COMERCIAL LTDA.", "CNPJ": "06.226.820/0001-82", "Valor": "558,60", "Mes/Ano": "09/2018"}, {"Vereador": " CAMILO CRIST\u00d3FARO", "Tipo_de_Gasto": "TELEFONE MOVEL", "Nome_Da_Empresa": "CLARO S.A.", "CNPJ": "40.432.544/0001-47", "Valor": "488,97", "Mes/Ano": "09/2018"}, {"Vereador": " CLAUDINHO DE SOUZA", "Tipo_de_Gasto": "COMBUSTIVEL", "Nome_Da_Empresa": "AUTO POSTO NOVO MORRO GRANDE LTDA", "CNPJ": "43.882.281/0001-66", "Valor": "527,43", "Mes/Ano": "09/2018"}, {"Vereador": " CLAUDINHO DE SOUZA", "Tipo_de_Gasto": "CONTRATA\u00c7AO DE PESSOA JURIDICA", "Nome_Da_Empresa": "MAZZA FC TECNOLOGIA DA INFORMACAO LTDA-ME", "CNPJ": "12.028.418/0001-96", "Valor": "2.000,00", "Mes/Ano": "09/2018"}, {"Vereador": " CLAUDINHO DE SOUZA", "Tipo_de_Gasto": "ELABORA\u00c7\u00c3O/MANUTEN\u00c7AO DE SITE/HOSPEDAGEM", "Nome_Da_Empresa": "FERRARI & CRINITI INFORM\u00c1TICA LTDA", "CNPJ": "03.515.743/0001-92", "Valor": "2.500,00", "Mes/Ano": "09/2018"}, {"Vereador": " CLAUDINHO DE SOUZA", "Tipo_de_Gasto": "INTERMEDIADO - CORREIOS", "Nome_Da_Empresa": "CAMARA MUNICIPAL DE S\u00c3O PAULO", "CNPJ": "50.176.288/0001-28", "Valor": "1.411,37", "Mes/Ano": "09/2018"}, {"Vereador": " CLAUDINHO DE SOUZA", "Tipo_de_Gasto": "INTERMEDIADO - LOCA\u00c7\u00c3O DE VE\u00cdCULOS", "Nome_Da_Empresa": "CAMARA MUNICIPAL DE S\u00c3O PAULO", "CNPJ": "50.176.288/0001-28", "Valor": "2.148,45", "Mes/Ano": "09/2018"}, {"Vereador": " CLAUDINHO DE SOUZA", "Tipo_de_Gasto": "MATERIAL DE ESCRITORIO E OUTROS MATERIAIS DE CONSUMO", "Nome_Da_Empresa": "HABILTECS DISTRIBUI\u00c7\u00c3O DE PE\u00c7AS E SERVI\u00c7OS LTDA.", "CNPJ": "96.409.172/0001-92", "Valor": "429,00", "Mes/Ano": "09/2018"}, {"Vereador": " CLAUDINHO DE SOUZA", "Tipo_de_Gasto": "TELEFONE FIXO", "Nome_Da_Empresa": "TELEFONICA BRASIL S/A", "CNPJ": "02.558.157/0001-62", "Valor": "601,73", "Mes/Ano": "09/2018"}, {"Vereador": " CLAUDINHO DE SOUZA", "Tipo_de_Gasto": "TELEFONE MOVEL", "Nome_Da_Empresa": "PORTO SEGURO TELECOMUNICA\u00c7\u00d5ES S.A.", "CNPJ": "11.281.004/0001-01", "Valor": "109,90", "Mes/Ano": "09/2018"}, {"Vereador": " CLAUDIO FONSECA", "Tipo_de_Gasto": "COMBUSTIVEL", "Nome_Da_Empresa": "AUTO POSTO LIDER-BANDEIRAS LTDA", "CNPJ": "05.025.949/0001-60", "Valor": "747,08", "Mes/Ano": "09/2018"}, {"Vereador": " CLAUDIO FONSECA", "Tipo_de_Gasto": "CONTRATA\u00c7AO DE PESSOA JURIDICA", "Nome_Da_Empresa": "TRAMPO INOVA\u00c7\u00d5ES MARKETING E CONST.TEC.DA INFOMR.", "CNPJ": "16.670.376/0001-43", "Valor": "5.000,00", "Mes/Ano": "09/2018"}, {"Vereador": " CLAUDIO FONSECA", "Tipo_de_Gasto": "CONTRATA\u00c7AO DE PESSOA JURIDICA", "Nome_Da_Empresa": "REVELE DESENVOLVIMENTO DIGITAL", "CNPJ": "16.727.438/0001-06", "Valor": "190,00", "Mes/Ano": "09/2018"}, {"Vereador": " CLAUDIO FONSECA", "Tipo_de_Gasto": "ELABORA\u00c7\u00c3O/MANUTEN\u00c7AO DE SITE/HOSPEDAGEM", "Nome_Da_Empresa": "WEBSIDE SERVI\u00c7OS EMPR LTDA ME", "CNPJ": "08.652.665/0001-91", "Valor": "49,90", "Mes/Ano": "09/2018"}, {"Vereador": " CLAUDIO FONSECA", "Tipo_de_Gasto": "INTERMEDIADO - CORREIOS", "Nome_Da_Empresa": "CAMARA MUNICIPAL DE S\u00c3O PAULO", "CNPJ": "50.176.288/0001-28", "Valor": "47,40", "Mes/Ano": "09/2018"}, {"Vereador": " CLAUDIO FONSECA", "Tipo_de_Gasto": "INTERMEDIADO - LOCA\u00c7\u00c3O DE VE\u00cdCULOS", "Nome_Da_Empresa": "CAMARA MUNICIPAL DE S\u00c3O PAULO", "CNPJ": "50.176.288/0001-28", "Valor": "2.148,45", "Mes/Ano": "09/2018"}, {"Vereador": " CLAUDIO FONSECA", "Tipo_de_Gasto": "LOCA\u00c7\u00c3O DE MOVEIS E EQUIPAMENTOS", "Nome_Da_Empresa": "ALOC LOCA\u00c7\u00c3O E COMERCIO DE EQUIPAMENTOS DE INFORM\u00c1TICA LTDA.", "CNPJ": "07.071.575/0001-44", "Valor": "1.295,00", "Mes/Ano": "09/2018"}, {"Vereador": " CLAUDIO FONSECA", "Tipo_de_Gasto": "LOCA\u00c7\u00c3O DE MOVEIS E EQUIPAMENTOS", "Nome_Da_Empresa": "K2G SUPRIMENTOS DE IMPRESS\u00c3O E INFORMATICA EIRELLI - ME", "CNPJ": "19.367.661/0001-88", "Valor": "741,00", "Mes/Ano": "09/2018"}, {"Vereador": " CLAUDIO FONSECA", "Tipo_de_Gasto": "MATERIAL DE ESCRITORIO E OUTROS MATERIAIS DE CONSUMO", "Nome_Da_Empresa": "K2G SUPRIMENTOS DE IMPRESS\u00c3O E INFORMATICA EIRELLI - ME", "CNPJ": "19.367.661/0001-88", "Valor": "2.160,00", "Mes/Ano": "09/2018"}, {"Vereador": " CLAUDIO FONSECA", "Tipo_de_Gasto": "PROVEDOR DE INTERNET", "Nome_Da_Empresa": "TELEFONICA BRASIL S/A", "CNPJ": "02.558.157/0001-62", "Valor": "101,23", "Mes/Ano": "09/2018"}, {"Vereador": " CONTE LOPES", "Tipo_de_Gasto": "CONTRATA\u00c7AO DE PESSOA JURIDICA", "Nome_Da_Empresa": "CONDE e DELL ARINGA - DESENVOLVIMENTO DE SOFTWARES LTDA - EPP", "CNPJ": "09.613.772/0001-73", "Valor": "430,00", "Mes/Ano": "09/2018"}, {"Vereador": " CONTE LOPES", "Tipo_de_Gasto": "INTERMEDIADO - CORREIOS", "Nome_Da_Empresa": "CAMARA MUNICIPAL DE S\u00c3O PAULO", "CNPJ": "50.176.288/0001-28", "Valor": "45,62", "Mes/Ano": "09/2018"}, {"Vereador": " CONTE LOPES", "Tipo_de_Gasto": "INTERMEDIADO - LOCA\u00c7\u00c3O DE VE\u00cdCULOS", "Nome_Da_Empresa": "CAMARA MUNICIPAL DE S\u00c3O PAULO", "CNPJ": "50.176.288/0001-28", "Valor": "2.148,45", "Mes/Ano": "09/2018"}, {"Vereador": " CONTE LOPES", "Tipo_de_Gasto": "LOCA\u00c7\u00c3O DE MOVEIS E EQUIPAMENTOS", "Nome_Da_Empresa": "ATTBRASIL TECNOLOGIA LOCA\u00c7\u00c3O E SOLU\u00c7\u00d5ES EM INFORMATICA LTDA EPP", "CNPJ": "22.392.165/0001-99", "Valor": "1.565,00", "Mes/Ano": "09/2018"}, {"Vereador": " CONTE LOPES", "Tipo_de_Gasto": "MATERIAL DE ESCRITORIO E OUTROS MATERIAIS DE CONSUMO", "Nome_Da_Empresa": "KALUNGA COMERCIO E IND. GR\u00c1FICA LTDA", "CNPJ": "43.283.811/0026-08", "Valor": "124,50", "Mes/Ano": "09/2018"}, {"Vereador": " CONTE LOPES", "Tipo_de_Gasto": "PROVEDOR DE INTERNET", "Nome_Da_Empresa": "TELEFONICA BRASIL S/A", "CNPJ": "02.558.157/0001-62", "Valor": "122,41", "Mes/Ano": "09/2018"}, {"Vereador": " DALTON SILVANO", "Tipo_de_Gasto": "COMBUSTIVEL", "Nome_Da_Empresa": "POSTO JENNER LTDA", "CNPJ": "61.699.179/0001-01", "Valor": "3.498,00", "Mes/Ano": "09/2018"}, {"Vereador": " DALTON SILVANO", "Tipo_de_Gasto": "COMPOSI\u00c7\u00c3O/ARTE/DIAGRAMA\u00c7\u00c3O/PRODU\u00c7\u00c3O/IMPRESSAO GRAFICA", "Nome_Da_Empresa": "LUIZ BAZZO FILHO - ME", "CNPJ": "03.169.981/0001-93", "Valor": "6.400,00", "Mes/Ano": "09/2018"}, {"Vereador": " DALTON SILVANO", "Tipo_de_Gasto": "COMPOSI\u00c7\u00c3O/ARTE/DIAGRAMA\u00c7\u00c3O/PRODU\u00c7\u00c3O/IMPRESSAO GRAFICA", "Nome_Da_Empresa": "CARLOS CELSO PIERRE GUIMARAES", "CNPJ": "29.324.949/0001-29", "Valor": "1.575,00", "Mes/Ano": "09/2018"}, {"Vereador": " DALTON SILVANO", "Tipo_de_Gasto": "CONTRATA\u00c7AO DE PESSOA JURIDICA", "Nome_Da_Empresa": "WORK LINE SYSTEM INFORM\u00c1TICA LTDA", "CNPJ": "67.002.329/0001-62", "Valor": "970,00", "Mes/Ano": "09/2018"}, {"Vereador": " DALTON SILVANO", "Tipo_de_Gasto": "ELABORA\u00c7\u00c3O/MANUTEN\u00c7AO DE SITE/HOSPEDAGEM", "Nome_Da_Empresa": "CARLOS CELSO PIERRE GUIMARAES", "CNPJ": "29.324.949/0001-29", "Valor": "7.100,00", "Mes/Ano": "09/2018"}, {"Vereador": " DALTON SILVANO", "Tipo_de_Gasto": "INTERMEDIADO - CORREIOS", "Nome_Da_Empresa": "CAMARA MUNICIPAL DE S\u00c3O PAULO", "CNPJ": "50.176.288/0001-28", "Valor": "3,70", "Mes/Ano": "09/2018"}, {"Vereador": " DALTON SILVANO", "Tipo_de_Gasto": "INTERMEDIADO - LOCA\u00c7\u00c3O DE VE\u00cdCULOS", "Nome_Da_Empresa": "CAMARA MUNICIPAL DE S\u00c3O PAULO", "CNPJ": "50.176.288/0001-28", "Valor": "2.148,45", "Mes/Ano": "09/2018"}, {"Vereador": " DALTON SILVANO", "Tipo_de_Gasto": "LOCA\u00c7\u00c3O DE MOVEIS E EQUIPAMENTOS", "Nome_Da_Empresa": "IRISARA COM\u00c9RCIO E SERVI\u00c7OS LTDA.", "CNPJ": "10.376.277/0001-77", "Valor": "400,00", "Mes/Ano": "09/2018"}, {"Vereador": " DALTON SILVANO", "Tipo_de_Gasto": "MATERIAL DE ESCRITORIO E OUTROS MATERIAIS DE CONSUMO", "Nome_Da_Empresa": "K2G SUPRIMENTOS DE IMPRESS\u00c3O E INFORMATICA EIRELLI - ME", "CNPJ": "19.367.661/0001-88", "Valor": "572,00", "Mes/Ano": "09/2018"}, {"Vereador": " DALTON SILVANO", "Tipo_de_Gasto": "TELEFONE FIXO", "Nome_Da_Empresa": "TELEFONICA BRASIL S/A", "CNPJ": "02.558.157/0001-62", "Valor": "242,66", "Mes/Ano": "09/2018"}, {"Vereador": " DALTON SILVANO", "Tipo_de_Gasto": "TELEFONE MOVEL", "Nome_Da_Empresa": "CLARO S.A.", "CNPJ": "40.432.544/0001-47", "Valor": "401,62", "Mes/Ano": "09/2018"}, {"Vereador": " DAVID SOARES", "Tipo_de_Gasto": "INTERMEDIADO - LOCA\u00c7\u00c3O DE VE\u00cdCULOS", "Nome_Da_Empresa": "CAMARA MUNICIPAL DE S\u00c3O PAULO", "CNPJ": "50.176.288/0001-28", "Valor": "2.148,45", "Mes/Ano": "09/2018"}, {"Vereador": " DAVID SOARES", "Tipo_de_Gasto": "MATERIAL DE ESCRITORIO E OUTROS MATERIAIS DE CONSUMO", "Nome_Da_Empresa": "CENTER PAPEIS COMERCIAL LTDA.", "CNPJ": "06.226.820/0001-82", "Valor": "299,45", "Mes/Ano": "09/2018"}, {"Vereador": " DONATO", "Tipo_de_Gasto": "COMBUSTIVEL", "Nome_Da_Empresa": "POSTO ENERGIA AUTOMOTIVA LTDA", "CNPJ": "19.499.974/0001-90", "Valor": "194,76", "Mes/Ano": "09/2018"}, {"Vereador": " DONATO", "Tipo_de_Gasto": "COMBUSTIVEL", "Nome_Da_Empresa": "MAXICAR AUTO SERVI\u00c7OS LTDA", "CNPJ": "46.158.986/0001-23", "Valor": "260,59", "Mes/Ano": "09/2018"}, {"Vereador": " DONATO", "Tipo_de_Gasto": "INTERMEDIADO - CORREIOS", "Nome_Da_Empresa": "CAMARA MUNICIPAL DE S\u00c3O PAULO", "CNPJ": "50.176.288/0001-28", "Valor": "19,90", "Mes/Ano": "09/2018"}, {"Vereador": " DONATO", "Tipo_de_Gasto": "INTERMEDIADO - LOCA\u00c7\u00c3O DE VE\u00cdCULOS", "Nome_Da_Empresa": "CAMARA MUNICIPAL DE S\u00c3O PAULO", "CNPJ": "50.176.288/0001-28", "Valor": "716,15", "Mes/Ano": "09/2018"}, {"Vereador": " DONATO", "Tipo_de_Gasto": "INTERMEDIADO - REPROGRAFIA (XEROX/ENCADERNA\u00c7\u00c3O)", "Nome_Da_Empresa": "CAMARA MUNICIPAL DE S\u00c3O PAULO", "CNPJ": "50.176.288/0001-28", "Valor": "168,00", "Mes/Ano": "09/2018"}, {"Vereador": " EDIR SALES", "Tipo_de_Gasto": "COMBUSTIVEL", "Nome_Da_Empresa": "RIP POSTOS DE SERVI\u00c7O E COM LTDA", "CNPJ": "43.720.218/0001-23", "Valor": "529,33", "Mes/Ano": "09/2018"}, {"Vereador": " EDIR SALES", "Tipo_de_Gasto": "CONTRATA\u00c7AO DE PESSOA JURIDICA", "Nome_Da_Empresa": "KITECH SOLUTIONS INFORMATICA LTDA.", "CNPJ": "16.912.244/0001-80", "Valor": "350,00", "Mes/Ano": "09/2018"}, {"Vereador": " EDIR SALES", "Tipo_de_Gasto": "CONTRATA\u00c7AO DE PESSOA JURIDICA", "Nome_Da_Empresa": "RODRIGO ALVES DA CRUZ DE BRITO", "CNPJ": "26.022.479/0001-50", "Valor": "3.500,00", "Mes/Ano": "09/2018"}, {"Vereador": " EDIR SALES", "Tipo_de_Gasto": "CONTRATA\u00c7AO DE PESSOA JURIDICA", "Nome_Da_Empresa": "ANDR\u00c9 SOARES BARROS", "CNPJ": "30.956.455/0001-46", "Valor": "3.500,00", "Mes/Ano": "09/2018"}, {"Vereador": " EDIR SALES", "Tipo_de_Gasto": "INTERMEDIADO - CORREIOS", "Nome_Da_Empresa": "CAMARA MUNICIPAL DE S\u00c3O PAULO", "CNPJ": "50.176.288/0001-28", "Valor": "29,33", "Mes/Ano": "09/2018"}, {"Vereador": " EDIR SALES", "Tipo_de_Gasto": "INTERMEDIADO - LOCA\u00c7\u00c3O DE VE\u00cdCULOS", "Nome_Da_Empresa": "CAMARA MUNICIPAL DE S\u00c3O PAULO", "CNPJ": "50.176.288/0001-28", "Valor": "2.148,45", "Mes/Ano": "09/2018"}, {"Vereador": " EDIR SALES", "Tipo_de_Gasto": "LOCA\u00c7\u00c3O DE MOVEIS E EQUIPAMENTOS", "Nome_Da_Empresa": "SOFT CLEVER INFORM\u00c1TICA LTDA. - ME", "CNPJ": "00.280.911/0001-10", "Valor": "850,00", "Mes/Ano": "09/2018"}, {"Vereador": " EDIR SALES", "Tipo_de_Gasto": "TELEFONE FIXO", "Nome_Da_Empresa": "TELEFONICA BRASIL S/A", "CNPJ": "02.558.157/0001-62", "Valor": "322,40", "Mes/Ano": "09/2018"}, {"Vereador": " EDIR SALES", "Tipo_de_Gasto": "TELEFONE MOVEL", "Nome_Da_Empresa": "TIM CELULAR S/A", "CNPJ": "04.206.050/0001-80", "Valor": "593,92", "Mes/Ano": "09/2018"}, {"Vereador": " EDUARDO MATARAZZO SUPLICY", "Tipo_de_Gasto": "COMPOSI\u00c7\u00c3O/ARTE/DIAGRAMA\u00c7\u00c3O/PRODU\u00c7\u00c3O/IMPRESSAO GRAFICA", "Nome_Da_Empresa": "WBL GRAFICA E EDITORA LTDA", "CNPJ": "08.142.850/0001-36", "Valor": "240,00", "Mes/Ano": "09/2018"}, {"Vereador": " EDUARDO MATARAZZO SUPLICY", "Tipo_de_Gasto": "COMPOSI\u00c7\u00c3O/ARTE/DIAGRAMA\u00c7\u00c3O/PRODU\u00c7\u00c3O/IMPRESSAO GRAFICA", "Nome_Da_Empresa": "FELIPE SPENCER NOBREGA CABRAL", "CNPJ": "24.992.302/0001-51", "Valor": "3.000,00", "Mes/Ano": "09/2018"}, {"Vereador": " EDUARDO MATARAZZO SUPLICY", "Tipo_de_Gasto": "CONTRATA\u00c7AO DE PESSOA JURIDICA", "Nome_Da_Empresa": "SOLARYS SOLU\u00c7\u00d5ES DIGITAIS LTDA-ME", "CNPJ": "08.648.207/0001-89", "Valor": "700,00", "Mes/Ano": "09/2018"}, {"Vereador": " EDUARDO MATARAZZO SUPLICY", "Tipo_de_Gasto": "ELABORA\u00c7\u00c3O/MANUTEN\u00c7AO DE SITE/HOSPEDAGEM", "Nome_Da_Empresa": "FELIPE SPENCER NOBREGA CABRAL", "CNPJ": "24.992.302/0001-51", "Valor": "5.000,00", "Mes/Ano": "09/2018"}, {"Vereador": " EDUARDO MATARAZZO SUPLICY", "Tipo_de_Gasto": "INTERMEDIADO - CORREIOS", "Nome_Da_Empresa": "CAMARA MUNICIPAL DE S\u00c3O PAULO", "CNPJ": "50.176.288/0001-28", "Valor": "42,35", "Mes/Ano": "09/2018"}, {"Vereador": " EDUARDO MATARAZZO SUPLICY", "Tipo_de_Gasto": "LOCA\u00c7\u00c3O DE MOVEIS E EQUIPAMENTOS", "Nome_Da_Empresa": "AS INFORMATICA LTDA.", "CNPJ": "62.931.548/0001-02", "Valor": "1.830,00", "Mes/Ano": "09/2018"}, {"Vereador": " EDUARDO MATARAZZO SUPLICY", "Tipo_de_Gasto": "TELEFONE FIXO", "Nome_Da_Empresa": "TELEFONICA BRASIL S/A", "CNPJ": "02.558.157/0001-62", "Valor": "323,58", "Mes/Ano": "09/2018"}, {"Vereador": " ELISEU GABRIEL", "Tipo_de_Gasto": "COMBUSTIVEL", "Nome_Da_Empresa": "SUNSET POSTOS DE SERV.E CONVENI\u00caNCIA LTDA", "CNPJ": "00.707.272/0001-26", "Valor": "506,63", "Mes/Ano": "09/2018"}, {"Vereador": " ELISEU GABRIEL", "Tipo_de_Gasto": "COMPOSI\u00c7\u00c3O/ARTE/DIAGRAMA\u00c7\u00c3O/PRODU\u00c7\u00c3O/IMPRESSAO GRAFICA", "Nome_Da_Empresa": "JEFFERSON ROBLES", "CNPJ": "30.960.307/0001-03", "Valor": "1.000,00", "Mes/Ano": "09/2018"}, {"Vereador": " ELISEU GABRIEL", "Tipo_de_Gasto": "COMPOSI\u00c7\u00c3O/ARTE/DIAGRAMA\u00c7\u00c3O/PRODU\u00c7\u00c3O/IMPRESSAO GRAFICA", "Nome_Da_Empresa": "A N GRAFICA LTDA ME", "CNPJ": "66.572.728/0001-04", "Valor": "2.520,00", "Mes/Ano": "09/2018"}, {"Vereador": " ELISEU GABRIEL", "Tipo_de_Gasto": "CONTRATA\u00c7AO DE PESSOA JURIDICA", "Nome_Da_Empresa": "UPLOAD SYSTEM CONSULTORIA COMERCIO DE SISTEMAS LTDA ME", "CNPJ": "05.670.753/0001-28", "Valor": "1.200,00", "Mes/Ano": "09/2018"}, {"Vereador": " ELISEU GABRIEL", "Tipo_de_Gasto": "INTERMEDIADO - CORREIOS", "Nome_Da_Empresa": "CAMARA MUNICIPAL DE S\u00c3O PAULO", "CNPJ": "50.176.288/0001-28", "Valor": "2.060,91", "Mes/Ano": "09/2018"}, {"Vereador": " ELISEU GABRIEL", "Tipo_de_Gasto": "INTERMEDIADO - LOCA\u00c7\u00c3O DE VE\u00cdCULOS", "Nome_Da_Empresa": "CAMARA MUNICIPAL DE S\u00c3O PAULO", "CNPJ": "50.176.288/0001-28", "Valor": "2.148,45", "Mes/Ano": "09/2018"}, {"Vereador": " ELISEU GABRIEL", "Tipo_de_Gasto": "LOCA\u00c7\u00c3O DE MOVEIS E EQUIPAMENTOS", "Nome_Da_Empresa": "KEY TEC NETWORK COM. E SERV. DE INFORM\u00c1TICA LTDA.", "CNPJ": "19.039.991/0001-44", "Valor": "1.514,00", "Mes/Ano": "09/2018"}, {"Vereador": " ELISEU GABRIEL", "Tipo_de_Gasto": "LOCA\u00c7\u00c3O DE MOVEIS E EQUIPAMENTOS", "Nome_Da_Empresa": "ATTBRASIL TECNOLOGIA LOCA\u00c7\u00c3O E SOLU\u00c7\u00d5ES EM INFORMATICA LTDA EPP", "CNPJ": "22.392.165/0001-99", "Valor": "735,00", "Mes/Ano": "09/2018"}, {"Vereador": " ELISEU GABRIEL", "Tipo_de_Gasto": "MATERIAL DE ESCRITORIO E OUTROS MATERIAIS DE CONSUMO", "Nome_Da_Empresa": "CENTER PAPEIS COMERCIAL LTDA.", "CNPJ": "06.226.820/0001-82", "Valor": "1.569,55", "Mes/Ano": "09/2018"}, {"Vereador": " ELISEU GABRIEL", "Tipo_de_Gasto": "TELEFONE MOVEL", "Nome_Da_Empresa": "TELEFONICA BRASIL S/A", "CNPJ": "02.558.157/0001-62", "Valor": "530,99", "Mes/Ano": "09/2018"}, {"Vereador": " FABIO RIVA", "Tipo_de_Gasto": "ASSINATURA DE JORNAIS E REVISTAS", "Nome_Da_Empresa": "EMPRESA FOLHA DA MANH\u00c3 S.A.", "CNPJ": "60.579.703/0031-63", "Valor": "358,80", "Mes/Ano": "09/2018"}, {"Vereador": " FABIO RIVA", "Tipo_de_Gasto": "LOCA\u00c7\u00c3O DE MOVEIS E EQUIPAMENTOS", "Nome_Da_Empresa": "ATTBRASIL TECNOLOGIA LOCA\u00c7\u00c3O E SOLU\u00c7\u00d5ES EM INFORMATICA LTDA EPP", "CNPJ": "22.392.165/0001-99", "Valor": "2.130,00", "Mes/Ano": "09/2018"}, {"Vereador": " FABIO RIVA", "Tipo_de_Gasto": "TELEFONE FIXO", "Nome_Da_Empresa": "TELEFONICA BRASIL S/A", "CNPJ": "02.558.157/0001-62", "Valor": "127,01", "Mes/Ano": "09/2018"}, {"Vereador": " FABIO RIVA", "Tipo_de_Gasto": "TELEFONE MOVEL", "Nome_Da_Empresa": "CLARO S.A.", "CNPJ": "40.432.544/0001-47", "Valor": "412,49", "Mes/Ano": "09/2018"}, {"Vereador": " FERNANDO HOLIDAY", "Tipo_de_Gasto": "INTERMEDIADO - CORREIOS", "Nome_Da_Empresa": "CAMARA MUNICIPAL DE S\u00c3O PAULO", "CNPJ": "50.176.288/0001-28", "Valor": "116,55", "Mes/Ano": "09/2018"}, {"Vereador": " FERNANDO HOLIDAY", "Tipo_de_Gasto": "LOCA\u00c7\u00c3O DE MOVEIS E EQUIPAMENTOS", "Nome_Da_Empresa": "ATTBRASIL TECNOLOGIA LOCA\u00c7\u00c3O E SOLU\u00c7\u00d5ES EM INFORMATICA LTDA EPP", "CNPJ": "22.392.165/0001-99", "Valor": "1.145,00", "Mes/Ano": "09/2018"}, {"Vereador": " FERNANDO HOLIDAY", "Tipo_de_Gasto": "MATERIAL DE ESCRITORIO E OUTROS MATERIAIS DE CONSUMO", "Nome_Da_Empresa": "CENTER PAPEIS COMERCIAL LTDA.", "CNPJ": "06.226.820/0001-82", "Valor": "263,35", "Mes/Ano": "09/2018"}, {"Vereador": " GEORGE HATO", "Tipo_de_Gasto": "COMBUSTIVEL", "Nome_Da_Empresa": "POSTO DE SERVI\u00c7OS POPULAR LTDA.", "CNPJ": "61.327.938/0001-05", "Valor": "1.564,43", "Mes/Ano": "09/2018"}, {"Vereador": " GEORGE HATO", "Tipo_de_Gasto": "CONTRATA\u00c7AO DE PESSOA JURIDICA", "Nome_Da_Empresa": "JO\u00c3O CARLOS FERREIRA CHAVES 30393339840", "CNPJ": "12.874.430/0001-11", "Valor": "2.000,00", "Mes/Ano": "09/2018"}, {"Vereador": " GEORGE HATO", "Tipo_de_Gasto": "CONTRATA\u00c7AO DE PESSOA JURIDICA", "Nome_Da_Empresa": "ATTBRASIL TECNOLOGIA LOCA\u00c7\u00c3O E SOLU\u00c7\u00d5ES EM INFORMATICA LTDA EPP", "CNPJ": "22.392.165/0001-99", "Valor": "855,00", "Mes/Ano": "09/2018"}, {"Vereador": " GEORGE HATO", "Tipo_de_Gasto": "CONTRATA\u00c7AO DE PESSOA JURIDICA", "Nome_Da_Empresa": "WORK LINE SYSTEM INFORM\u00c1TICA LTDA", "CNPJ": "67.002.329/0001-62", "Valor": "970,00", "Mes/Ano": "09/2018"}, {"Vereador": " GEORGE HATO", "Tipo_de_Gasto": "INTERMEDIADO - CORREIOS", "Nome_Da_Empresa": "CAMARA MUNICIPAL DE S\u00c3O PAULO", "CNPJ": "50.176.288/0001-28", "Valor": "9,25", "Mes/Ano": "09/2018"}, {"Vereador": " GEORGE HATO", "Tipo_de_Gasto": "INTERMEDIADO - LOCA\u00c7\u00c3O DE VE\u00cdCULOS", "Nome_Da_Empresa": "CAMARA MUNICIPAL DE S\u00c3O PAULO", "CNPJ": "50.176.288/0001-28", "Valor": "2.148,45", "Mes/Ano": "09/2018"}, {"Vereador": " GEORGE HATO", "Tipo_de_Gasto": "LOCA\u00c7\u00c3O DE MOVEIS E EQUIPAMENTOS", "Nome_Da_Empresa": "ATTBRASIL TECNOLOGIA LOCA\u00c7\u00c3O E SOLU\u00c7\u00d5ES EM INFORMATICA LTDA EPP", "CNPJ": "22.392.165/0001-99", "Valor": "3.375,00", "Mes/Ano": "09/2018"}, {"Vereador": " GEORGE HATO", "Tipo_de_Gasto": "MATERIAL DE ESCRITORIO E OUTROS MATERIAIS DE CONSUMO", "Nome_Da_Empresa": "CENTER PAPEIS COMERCIAL LTDA.", "CNPJ": "06.226.820/0001-82", "Valor": "47,90", "Mes/Ano": "09/2018"}, {"Vereador": " GEORGE HATO", "Tipo_de_Gasto": "TELEFONE FIXO", "Nome_Da_Empresa": "TELEFONICA BRASIL S/A", "CNPJ": "02.558.157/0001-62", "Valor": "300,01", "Mes/Ano": "09/2018"}, {"Vereador": " GEORGE HATO", "Tipo_de_Gasto": "TELEFONE MOVEL", "Nome_Da_Empresa": "TELEFONICA BRASIL S/A", "CNPJ": "02.558.157/0001-62", "Valor": "590,79", "Mes/Ano": "09/2018"}, {"Vereador": " GILSON BARRETO", "Tipo_de_Gasto": "COMBUSTIVEL", "Nome_Da_Empresa": "AUTO POSTO LIRITAPURA LTDA", "CNPJ": "07.441.746/0001-80", "Valor": "1.008,35", "Mes/Ano": "09/2018"}, {"Vereador": " GILSON BARRETO", "Tipo_de_Gasto": "COMPOSI\u00c7\u00c3O/ARTE/DIAGRAMA\u00c7\u00c3O/PRODU\u00c7\u00c3O/IMPRESSAO GRAFICA", "Nome_Da_Empresa": "EDITORA GR\u00c1FICA PANA LTDA.", "CNPJ": "02.740.573/0001-87", "Valor": "7.820,00", "Mes/Ano": "09/2018"}, {"Vereador": " GILSON BARRETO", "Tipo_de_Gasto": "CONTRATA\u00c7AO DE PESSOA JURIDICA", "Nome_Da_Empresa": "DORIVAL MARTINS TECNOLOGIA ME", "CNPJ": "28.967.422/0001-50", "Valor": "5.000,00", "Mes/Ano": "09/2018"}, {"Vereador": " GILSON BARRETO", "Tipo_de_Gasto": "ELABORA\u00c7\u00c3O/MANUTEN\u00c7AO DE SITE/HOSPEDAGEM", "Nome_Da_Empresa": "T.O.RIBEIRO - ME", "CNPJ": "11.186.215/0001-65", "Valor": "1.184,76", "Mes/Ano": "09/2018"}, {"Vereador": " GILSON BARRETO", "Tipo_de_Gasto": "INTERMEDIADO - CORREIOS", "Nome_Da_Empresa": "CAMARA MUNICIPAL DE S\u00c3O PAULO", "CNPJ": "50.176.288/0001-28", "Valor": "3,70", "Mes/Ano": "09/2018"}, {"Vereador": " GILSON BARRETO", "Tipo_de_Gasto": "INTERMEDIADO - LOCA\u00c7\u00c3O DE VE\u00cdCULOS", "Nome_Da_Empresa": "CAMARA MUNICIPAL DE S\u00c3O PAULO", "CNPJ": "50.176.288/0001-28", "Valor": "2.148,45", "Mes/Ano": "09/2018"}, {"Vereador": " GILSON BARRETO", "Tipo_de_Gasto": "LOCA\u00c7\u00c3O DE MOVEIS E EQUIPAMENTOS", "Nome_Da_Empresa": "CESAR CALIL ELETR\u00d4NICA ME", "CNPJ": "06.288.041/0001-01", "Valor": "3.350,00", "Mes/Ano": "09/2018"}, {"Vereador": " GILSON BARRETO", "Tipo_de_Gasto": "LOCA\u00c7\u00c3O DE MOVEIS E EQUIPAMENTOS", "Nome_Da_Empresa": "FMJ COM\u00c9RCIO E ASSISTENCIA T\u00c9CNICA EM COPIADORAS LTDA ME", "CNPJ": "07.915.380/0001-33", "Valor": "300,00", "Mes/Ano": "09/2018"}, {"Vereador": " GILSON BARRETO", "Tipo_de_Gasto": "MATERIAL DE ESCRITORIO E OUTROS MATERIAIS DE CONSUMO", "Nome_Da_Empresa": "FMJ COM\u00c9RCIO E ASSISTENCIA T\u00c9CNICA EM COPIADORAS LTDA ME", "CNPJ": "07.915.380/0001-33", "Valor": "409,90", "Mes/Ano": "09/2018"}, {"Vereador": " GILSON BARRETO", "Tipo_de_Gasto": "MATERIAL DE ESCRITORIO E OUTROS MATERIAIS DE CONSUMO", "Nome_Da_Empresa": "KALUNGA COM\u00c9RCIO E IND\u00daSTRIA GR\u00c1FICA LTDA", "CNPJ": "43.283.811/0018-06", "Valor": "43,60", "Mes/Ano": "09/2018"}, {"Vereador": " GILSON BARRETO", "Tipo_de_Gasto": "MATERIAL DE ESCRITORIO E OUTROS MATERIAIS DE CONSUMO", "Nome_Da_Empresa": "ARMARINHOS FERNANDO LTDA", "CNPJ": "48.076.228/0009-49", "Valor": "51,20", "Mes/Ano": "09/2018"}, {"Vereador": " GILSON BARRETO", "Tipo_de_Gasto": "TELEFONE MOVEL", "Nome_Da_Empresa": "TELEFONICA BRASIL S/A", "CNPJ": "02.558.157/0001-62", "Valor": "149,99", "Mes/Ano": "09/2018"}, {"Vereador": " ISAC FELIX", "Tipo_de_Gasto": "COMBUSTIVEL", "Nome_Da_Empresa": "PANAMBY 10 POSTO DE SERVI\u00c7OS E CONVENIENCIA EIRELI", "CNPJ": "21.781.198/0001-68", "Valor": "1.763,29", "Mes/Ano": "09/2018"}, {"Vereador": " ISAC FELIX", "Tipo_de_Gasto": "CONTRATA\u00c7AO DE PESSOA JURIDICA", "Nome_Da_Empresa": "AGATHA PERALTA DO AMARAL", "CNPJ": "22.983.210/0001-80", "Valor": "3.000,00", "Mes/Ano": "09/2018"}, {"Vereador": " ISAC FELIX", "Tipo_de_Gasto": "CONTRATA\u00c7AO DE PESSOA JURIDICA", "Nome_Da_Empresa": "WORK LINE SYSTEM INFORM\u00c1TICA LTDA", "CNPJ": "67.002.329/0001-62", "Valor": "970,00", "Mes/Ano": "09/2018"}, {"Vereador": " ISAC FELIX", "Tipo_de_Gasto": "INTERMEDIADO - CORREIOS", "Nome_Da_Empresa": "CAMARA MUNICIPAL DE S\u00c3O PAULO", "CNPJ": "50.176.288/0001-28", "Valor": "2.414,93", "Mes/Ano": "09/2018"}, {"Vereador": " ISAC FELIX", "Tipo_de_Gasto": "INTERMEDIADO - LOCA\u00c7\u00c3O DE VE\u00cdCULOS", "Nome_Da_Empresa": "CAMARA MUNICIPAL DE S\u00c3O PAULO", "CNPJ": "50.176.288/0001-28", "Valor": "2.148,45", "Mes/Ano": "09/2018"}, {"Vereador": " ISAC FELIX", "Tipo_de_Gasto": "LOCA\u00c7\u00c3O DE MOVEIS E EQUIPAMENTOS", "Nome_Da_Empresa": "LOC PRIME LOCA\u00c7\u00c3O, COM\u00c9RCIO E SERVI\u00c7OS LTDA.ME", "CNPJ": "09.387.547/0001-66", "Valor": "360,00", "Mes/Ano": "09/2018"}, {"Vereador": " ISAC FELIX", "Tipo_de_Gasto": "MATERIAL DE ESCRITORIO E OUTROS MATERIAIS DE CONSUMO", "Nome_Da_Empresa": "CENTER PAPEIS COMERCIAL LTDA.", "CNPJ": "06.226.820/0001-82", "Valor": "47,90", "Mes/Ano": "09/2018"}, {"Vereador": " ISAC FELIX", "Tipo_de_Gasto": "MATERIAL DE ESCRITORIO E OUTROS MATERIAIS DE CONSUMO", "Nome_Da_Empresa": "KALUNGA COM\u00c9RCIO E IND\u00daSTRIA GR\u00c1FICA LTDA", "CNPJ": "43.283.811/0032-56", "Valor": "908,89", "Mes/Ano": "09/2018"}, {"Vereador": " JAIR TATTO", "Tipo_de_Gasto": "COMBUSTIVEL", "Nome_Da_Empresa": "POSTO DE SERVI\u00c7OS ANTONIO PAES LTDA", "CNPJ": "62.409.305/0001-09", "Valor": "1.115,52", "Mes/Ano": "09/2018"}, {"Vereador": " JAIR TATTO", "Tipo_de_Gasto": "COMPOSI\u00c7\u00c3O/ARTE/DIAGRAMA\u00c7\u00c3O/PRODU\u00c7\u00c3O/IMPRESSAO GRAFICA", "Nome_Da_Empresa": "F\u00c1BRICA SETE GR\u00c1FICA E EDITORA LTDA - ME", "CNPJ": "00.651.238/0001-87", "Valor": "5.000,00", "Mes/Ano": "09/2018"}, {"Vereador": " JAIR TATTO", "Tipo_de_Gasto": "COMPOSI\u00c7\u00c3O/ARTE/DIAGRAMA\u00c7\u00c3O/PRODU\u00c7\u00c3O/IMPRESSAO GRAFICA", "Nome_Da_Empresa": "VISTAR PRESTA\u00c7\u00c3O DE SERVI\u00c7OS DE DIGITA\u00c7\u00c3O LTDA ME", "CNPJ": "08.689.647/0001-84", "Valor": "3.000,00", "Mes/Ano": "09/2018"}, {"Vereador": " JAIR TATTO", "Tipo_de_Gasto": "CONTRATA\u00c7AO DE PESSOA JURIDICA", "Nome_Da_Empresa": "CONDE e DELL ARINGA - DESENVOLVIMENTO DE SOFTWARES LTDA - EPP", "CNPJ": "09.613.772/0001-73", "Valor": "161,00", "Mes/Ano": "09/2018"}, {"Vereador": " JAIR TATTO", "Tipo_de_Gasto": "CONTRATA\u00c7AO DE PESSOA JURIDICA", "Nome_Da_Empresa": "PROSPECT COMUNICA\u00c7\u00c3O E MARKETING LTDA-ME", "CNPJ": "26.885.016/0001-12", "Valor": "1.200,00", "Mes/Ano": "09/2018"}, {"Vereador": " JAIR TATTO", "Tipo_de_Gasto": "CONTRATA\u00c7AO DE PESSOA JURIDICA", "Nome_Da_Empresa": "SANDRA DA CRUZ SANTANA NOGUEIRA 24753582892", "CNPJ": "28.040.815/0001-13", "Valor": "3.500,00", "Mes/Ano": "09/2018"}, {"Vereador": " JAIR TATTO", "Tipo_de_Gasto": "ELABORA\u00c7\u00c3O/MANUTEN\u00c7AO DE SITE/HOSPEDAGEM", "Nome_Da_Empresa": "VISTAR PRESTA\u00c7\u00c3O DE SERVI\u00c7OS DE DIGITA\u00c7\u00c3O LTDA ME", "CNPJ": "08.689.647/0001-84", "Valor": "2.000,00", "Mes/Ano": "09/2018"}, {"Vereador": " JAIR TATTO", "Tipo_de_Gasto": "INTERMEDIADO - CORREIOS", "Nome_Da_Empresa": "CAMARA MUNICIPAL DE S\u00c3O PAULO", "CNPJ": "50.176.288/0001-28", "Valor": "314,08", "Mes/Ano": "09/2018"}, {"Vereador": " JAIR TATTO", "Tipo_de_Gasto": "INTERMEDIADO - LOCA\u00c7\u00c3O DE VE\u00cdCULOS", "Nome_Da_Empresa": "CAMARA MUNICIPAL DE S\u00c3O PAULO", "CNPJ": "50.176.288/0001-28", "Valor": "2.148,45", "Mes/Ano": "09/2018"}, {"Vereador": " JAIR TATTO", "Tipo_de_Gasto": "PROVEDOR DE INTERNET", "Nome_Da_Empresa": "TELEFONICA BRASIL S/A", "CNPJ": "02.558.157/0001-62", "Valor": "25,16", "Mes/Ano": "09/2018"}, {"Vereador": " JAIR TATTO", "Tipo_de_Gasto": "TELEFONE MOVEL", "Nome_Da_Empresa": "NEXTEL TELECOMUNICA\u00c7\u00d5ES LTDA", "CNPJ": "66.970.229/0001-67", "Valor": "266,65", "Mes/Ano": "09/2018"}, {"Vereador": " JO\u00c3O JORGE", "Tipo_de_Gasto": "COMPOSI\u00c7\u00c3O/ARTE/DIAGRAMA\u00c7\u00c3O/PRODU\u00c7\u00c3O/IMPRESSAO GRAFICA", "Nome_Da_Empresa": "JG EDITORA GR\u00c1FICA COMPLETA LTDA EPP", "CNPJ": "06.370.081/0001-06", "Valor": "5.100,00", "Mes/Ano": "09/2018"}, {"Vereador": " JO\u00c3O JORGE", "Tipo_de_Gasto": "CONTRATA\u00c7AO DE PESSOA JURIDICA", "Nome_Da_Empresa": "MC4 MARKETING E NEGOCIOS DIGITAIS LTDA - EPP", "CNPJ": "20.036.300/0001-38", "Valor": "2.500,00", "Mes/Ano": "09/2018"}, {"Vereador": " JO\u00c3O JORGE", "Tipo_de_Gasto": "CONTRATA\u00c7AO DE PESSOA JURIDICA", "Nome_Da_Empresa": "WORK LINE SYSTEM INFORM\u00c1TICA LTDA", "CNPJ": "67.002.329/0001-62", "Valor": "970,00", "Mes/Ano": "09/2018"}, {"Vereador": " JO\u00c3O JORGE", "Tipo_de_Gasto": "ELABORA\u00c7\u00c3O/MANUTEN\u00c7AO DE SITE/HOSPEDAGEM", "Nome_Da_Empresa": "MC4 MARKETING E NEGOCIOS DIGITAIS LTDA - EPP", "CNPJ": "20.036.300/0001-38", "Valor": "5.000,00", "Mes/Ano": "09/2018"}, {"Vereador": " JO\u00c3O JORGE", "Tipo_de_Gasto": "INTERMEDIADO - LOCA\u00c7\u00c3O DE VE\u00cdCULOS", "Nome_Da_Empresa": "CAMARA MUNICIPAL DE S\u00c3O PAULO", "CNPJ": "50.176.288/0001-28", "Valor": "2.148,45", "Mes/Ano": "09/2018"}, {"Vereador": " JO\u00c3O JORGE", "Tipo_de_Gasto": "LOCA\u00c7\u00c3O DE MOVEIS E EQUIPAMENTOS", "Nome_Da_Empresa": "K2G SUPRIMENTOS DE IMPRESS\u00c3O E INFORMATICA EIRELLI - ME", "CNPJ": "19.367.661/0001-88", "Valor": "2.730,00", "Mes/Ano": "09/2018"}, {"Vereador": " JOS\u00c9 POLICE NETO", "Tipo_de_Gasto": "COMPOSI\u00c7\u00c3O/ARTE/DIAGRAMA\u00c7\u00c3O/PRODU\u00c7\u00c3O/IMPRESSAO GRAFICA", "Nome_Da_Empresa": "RWC - GR\u00c1FICA E EDITORA LTDA ME", "CNPJ": "24.827.045/0001-00", "Valor": "3.650,00", "Mes/Ano": "09/2018"}, {"Vereador": " JOS\u00c9 POLICE NETO", "Tipo_de_Gasto": "INTERMEDIADO - CORREIOS", "Nome_Da_Empresa": "CAMARA MUNICIPAL DE S\u00c3O PAULO", "CNPJ": "50.176.288/0001-28", "Valor": "35,55", "Mes/Ano": "09/2018"}, {"Vereador": " JOS\u00c9 POLICE NETO", "Tipo_de_Gasto": "INTERMEDIADO - REPROGRAFIA (XEROX/ENCADERNA\u00c7\u00c3O)", "Nome_Da_Empresa": "CAMARA MUNICIPAL DE S\u00c3O PAULO", "CNPJ": "50.176.288/0001-28", "Valor": "37,80", "Mes/Ano": "09/2018"}, {"Vereador": " JOS\u00c9 POLICE NETO", "Tipo_de_Gasto": "LOCA\u00c7\u00c3O DE MOVEIS E EQUIPAMENTOS", "Nome_Da_Empresa": "FMJ COM\u00c9RCIO E ASSISTENCIA T\u00c9CNICA EM COPIADORAS LTDA ME", "CNPJ": "07.915.380/0001-33", "Valor": "798,50", "Mes/Ano": "09/2018"}, {"Vereador": " JOS\u00c9 POLICE NETO", "Tipo_de_Gasto": "MATERIAL DE ESCRITORIO E OUTROS MATERIAIS DE CONSUMO", "Nome_Da_Empresa": "CENTER PAPEIS COMERCIAL LTDA.", "CNPJ": "06.226.820/0001-82", "Valor": "474,85", "Mes/Ano": "09/2018"}, {"Vereador": " JOS\u00c9 POLICE NETO", "Tipo_de_Gasto": "MATERIAL DE ESCRITORIO E OUTROS MATERIAIS DE CONSUMO", "Nome_Da_Empresa": "FMJ COM\u00c9RCIO E ASSISTENCIA T\u00c9CNICA EM COPIADORAS LTDA ME", "CNPJ": "07.915.380/0001-33", "Valor": "409,90", "Mes/Ano": "09/2018"}, {"Vereador": " JULIANA CARDOSO", "Tipo_de_Gasto": "ASSINATURA DE JORNAIS E REVISTAS", "Nome_Da_Empresa": "EDITORA GLOBO S.A. PARQUE GR\u00c1FICO", "CNPJ": "04.067.191/0007-55", "Valor": "770,40", "Mes/Ano": "09/2018"}, {"Vereador": " JULIANA CARDOSO", "Tipo_de_Gasto": "ASSINATURA DE JORNAIS E REVISTAS", "Nome_Da_Empresa": "S.A O ESTADO DE S. PAULO", "CNPJ": "61.533.949/0001-41", "Valor": "108,90", "Mes/Ano": "09/2018"}, {"Vereador": " JULIANA CARDOSO", "Tipo_de_Gasto": "COMBUSTIVEL", "Nome_Da_Empresa": "POSTO DE SERVI\u00c7OS CCS LTDA", "CNPJ": "52.661.501/0001-12", "Valor": "1.014,82", "Mes/Ano": "09/2018"}, {"Vereador": " JULIANA CARDOSO", "Tipo_de_Gasto": "CONTRATA\u00c7AO DE PESSOA JURIDICA", "Nome_Da_Empresa": "VIZION GEST\u00c3O DE NEGOCIOS EMPRESARIAIS LTDA", "CNPJ": "07.979.987/0001-87", "Valor": "599,90", "Mes/Ano": "09/2018"}, {"Vereador": " JULIANA CARDOSO", "Tipo_de_Gasto": "ELABORA\u00c7\u00c3O/MANUTEN\u00c7AO DE SITE/HOSPEDAGEM", "Nome_Da_Empresa": "CAMILA CRISTINA FURCHI 29818251865", "CNPJ": "15.686.221/0001-32", "Valor": "4.100,00", "Mes/Ano": "09/2018"}, {"Vereador": " JULIANA CARDOSO", "Tipo_de_Gasto": "INTERMEDIADO - LOCA\u00c7\u00c3O DE VE\u00cdCULOS", "Nome_Da_Empresa": "CAMARA MUNICIPAL DE S\u00c3O PAULO", "CNPJ": "50.176.288/0001-28", "Valor": "2.148,45", "Mes/Ano": "09/2018"}, {"Vereador": " JULIANA CARDOSO", "Tipo_de_Gasto": "LOCA\u00c7\u00c3O DE MOVEIS E EQUIPAMENTOS", "Nome_Da_Empresa": "MPL COMPANY S/C LTDA - ME", "CNPJ": "02.734.547/0001-46", "Valor": "400,00", "Mes/Ano": "09/2018"}, {"Vereador": " JULIANA CARDOSO", "Tipo_de_Gasto": "LOCA\u00c7\u00c3O DE MOVEIS E EQUIPAMENTOS", "Nome_Da_Empresa": "ATTBRASIL TECNOLOGIA LOCA\u00c7\u00c3O E SOLU\u00c7\u00d5ES EM INFORMATICA LTDA EPP", "CNPJ": "22.392.165/0001-99", "Valor": "2.180,00", "Mes/Ano": "09/2018"}, {"Vereador": " JULIANA CARDOSO", "Tipo_de_Gasto": "MATERIAL DE ESCRITORIO E OUTROS MATERIAIS DE CONSUMO", "Nome_Da_Empresa": "CENTER PAPEIS COMERCIAL LTDA.", "CNPJ": "06.226.820/0001-82", "Valor": "1.312,10", "Mes/Ano": "09/2018"}, {"Vereador": " JULIANA CARDOSO", "Tipo_de_Gasto": "PROVEDOR DE INTERNET", "Nome_Da_Empresa": "CLARO S.A.", "CNPJ": "40.432.544/0001-47", "Valor": "352,96", "Mes/Ano": "09/2018"}, {"Vereador": " JULIANA CARDOSO", "Tipo_de_Gasto": "TELEFONE FIXO", "Nome_Da_Empresa": "TELEFONICA BRASIL S/A", "CNPJ": "02.558.157/0001-62", "Valor": "182,41", "Mes/Ano": "09/2018"}, {"Vereador": " JULIANA CARDOSO", "Tipo_de_Gasto": "TELEFONE MOVEL", "Nome_Da_Empresa": "CLARO S.A.", "CNPJ": "40.432.544/0001-47", "Valor": "418,19", "Mes/Ano": "09/2018"}, {"Vereador": " LUIZ PASCHOAL", "Tipo_de_Gasto": "INTERMEDIADO - LOCA\u00c7\u00c3O DE VE\u00cdCULOS", "Nome_Da_Empresa": "CAMARA MUNICIPAL DE S\u00c3O PAULO", "CNPJ": "50.176.288/0001-28", "Valor": "2.148,45", "Mes/Ano": "09/2018"}, {"Vereador": " LUIZ PASCHOAL", "Tipo_de_Gasto": "INTERMEDIADO - REPROGRAFIA (XEROX/ENCADERNA\u00c7\u00c3O)", "Nome_Da_Empresa": "CAMARA MUNICIPAL DE S\u00c3O PAULO", "CNPJ": "50.176.288/0001-28", "Valor": "0,21", "Mes/Ano": "09/2018"}, {"Vereador": " MANOEL DEL RIO", "Tipo_de_Gasto": "CONTRATA\u00c7AO DE PESSOA JURIDICA", "Nome_Da_Empresa": "IP3 CONSULTORIA DE COMUNICACAO, INOV.TECN. E INVEST.LTDA", "CNPJ": "00.638.847/0001-04", "Valor": "8.000,00", "Mes/Ano": "09/2018"}, {"Vereador": " MANOEL DEL RIO", "Tipo_de_Gasto": "LOCA\u00c7\u00c3O DE MOVEIS E EQUIPAMENTOS", "Nome_Da_Empresa": "FMJ COM\u00c9RCIO E ASSISTENCIA T\u00c9CNICA EM COPIADORAS LTDA ME", "CNPJ": "07.915.380/0001-33", "Valor": "500,00", "Mes/Ano": "09/2018"}, {"Vereador": " M\u00c1RIO COVAS NETO", "Tipo_de_Gasto": "ASSINATURA DE JORNAIS E REVISTAS", "Nome_Da_Empresa": "S.A O ESTADO DE S. PAULO", "CNPJ": "61.533.949/0001-41", "Valor": "42,90", "Mes/Ano": "09/2018"}, {"Vereador": " M\u00c1RIO COVAS NETO", "Tipo_de_Gasto": "CONTRATA\u00c7AO DE PESSOA JURIDICA", "Nome_Da_Empresa": "SOLARYS SOLU\u00c7\u00d5ES DIGITAIS LTDA-ME", "CNPJ": "08.648.207/0001-89", "Valor": "700,00", "Mes/Ano": "09/2018"}, {"Vereador": " M\u00c1RIO COVAS NETO", "Tipo_de_Gasto": "ELABORA\u00c7\u00c3O/MANUTEN\u00c7AO DE SITE/HOSPEDAGEM", "Nome_Da_Empresa": "SAMPA COMUNICA\u00c7\u00c3O E MARKETING LTDA.", "CNPJ": "11.178.351/0001-03", "Valor": "8.000,00", "Mes/Ano": "09/2018"}, {"Vereador": " M\u00c1RIO COVAS NETO", "Tipo_de_Gasto": "INTERMEDIADO - CORREIOS", "Nome_Da_Empresa": "CAMARA MUNICIPAL DE S\u00c3O PAULO", "CNPJ": "50.176.288/0001-28", "Valor": "28,10", "Mes/Ano": "09/2018"}, {"Vereador": " M\u00c1RIO COVAS NETO", "Tipo_de_Gasto": "LOCA\u00c7\u00c3O DE VE\u00cdCULOS", "Nome_Da_Empresa": "LEAD TERCEIRIZA\u00c7\u00c3O DE FROTAS DE VE\u00cdCULOS LTDA", "CNPJ": "21.394.088/0001-43", "Valor": "2.148,45", "Mes/Ano": "09/2018"}, {"Vereador": " M\u00c1RIO COVAS NETO", "Tipo_de_Gasto": "MATERIAL DE ESCRITORIO E OUTROS MATERIAIS DE CONSUMO", "Nome_Da_Empresa": "CENTER PAPEIS COMERCIAL LTDA.", "CNPJ": "06.226.820/0001-82", "Valor": "1.221,80", "Mes/Ano": "09/2018"}, {"Vereador": " M\u00c1RIO COVAS NETO", "Tipo_de_Gasto": "TELEFONE MOVEL", "Nome_Da_Empresa": "NEXTEL TELECOMUNICA\u00c7\u00d5ES LTDA", "CNPJ": "66.970.229/0001-67", "Valor": "304,97", "Mes/Ano": "09/2018"}, {"Vereador": " MILTON LEITE", "Tipo_de_Gasto": "COMBUSTIVEL", "Nome_Da_Empresa": "AUTO POSTO PORTAL DE INTERLAGOS LTDA", "CNPJ": "10.203.913/0001-69", "Valor": "459,00", "Mes/Ano": "09/2018"}, {"Vereador": " MILTON LEITE", "Tipo_de_Gasto": "INTERMEDIADO - LOCA\u00c7\u00c3O DE VE\u00cdCULOS", "Nome_Da_Empresa": "CAMARA MUNICIPAL DE S\u00c3O PAULO", "CNPJ": "50.176.288/0001-28", "Valor": "2.148,45", "Mes/Ano": "09/2018"}, {"Vereador": " NATALINI", "Tipo_de_Gasto": "COMBUSTIVEL", "Nome_Da_Empresa": "ZONTA AUTO POSTO LTDA.-", "CNPJ": "62.558.309/0001-59", "Valor": "539,98", "Mes/Ano": "09/2018"}, {"Vereador": " NATALINI", "Tipo_de_Gasto": "COMPOSI\u00c7\u00c3O/ARTE/DIAGRAMA\u00c7\u00c3O/PRODU\u00c7\u00c3O/IMPRESSAO GRAFICA", "Nome_Da_Empresa": "EDILSON NASCIMENTO SILVA 32544285877", "CNPJ": "23.820.359/0001-00", "Valor": "144,00", "Mes/Ano": "09/2018"}, {"Vereador": " NATALINI", "Tipo_de_Gasto": "CONTRATA\u00c7AO DE PESSOA JURIDICA", "Nome_Da_Empresa": "ISAURA BACCO 37788372811", "CNPJ": "29.085.904/0001-49", "Valor": "4.000,00", "Mes/Ano": "09/2018"}, {"Vereador": " NATALINI", "Tipo_de_Gasto": "EVENTOS/SEMINARIOS", "Nome_Da_Empresa": "ANGGULO COMUNICA\u00c7\u00c3O ESTRAT\u00c9GICA LTDA", "CNPJ": "06.912.116/0001-83", "Valor": "6.000,00", "Mes/Ano": "09/2018"}, {"Vereador": " NATALINI", "Tipo_de_Gasto": "INTERMEDIADO - LOCA\u00c7\u00c3O DE VE\u00cdCULOS", "Nome_Da_Empresa": "CAMARA MUNICIPAL DE S\u00c3O PAULO", "CNPJ": "50.176.288/0001-28", "Valor": "2.148,45", "Mes/Ano": "09/2018"}, {"Vereador": " NATALINI", "Tipo_de_Gasto": "LOCA\u00c7\u00c3O DE MOVEIS E EQUIPAMENTOS", "Nome_Da_Empresa": "SOFT CLEVER INFORM\u00c1TICA LTDA. - ME", "CNPJ": "00.280.911/0001-10", "Valor": "1.563,68", "Mes/Ano": "09/2018"}, {"Vereador": " NATALINI", "Tipo_de_Gasto": "LOCA\u00c7\u00c3O DE MOVEIS E EQUIPAMENTOS", "Nome_Da_Empresa": "FMJ COM\u00c9RCIO E ASSISTENCIA T\u00c9CNICA EM COPIADORAS LTDA ME", "CNPJ": "07.915.380/0001-33", "Valor": "400,00", "Mes/Ano": "09/2018"}, {"Vereador": " NATALINI", "Tipo_de_Gasto": "MATERIAL DE ESCRITORIO E OUTROS MATERIAIS DE CONSUMO", "Nome_Da_Empresa": "K2G SUPRIMENTOS DE IMPRESS\u00c3O E INFORMATICA EIRELLI - ME", "CNPJ": "19.367.661/0001-88", "Valor": "185,00", "Mes/Ano": "09/2018"}, {"Vereador": " NATALINI", "Tipo_de_Gasto": "TELEFONE FIXO", "Nome_Da_Empresa": "TELEFONICA BRASIL S/A", "CNPJ": "02.558.157/0001-62", "Valor": "232,87", "Mes/Ano": "09/2018"}, {"Vereador": " NOEMI NONATO", "Tipo_de_Gasto": "COMBUSTIVEL", "Nome_Da_Empresa": "CENTRO AUTOMOTIVO ALTEROSA LTDA", "CNPJ": "02.072.923/0001-84", "Valor": "794,52", "Mes/Ano": "09/2018"}, {"Vereador": " NOEMI NONATO", "Tipo_de_Gasto": "COMPOSI\u00c7\u00c3O/ARTE/DIAGRAMA\u00c7\u00c3O/PRODU\u00c7\u00c3O/IMPRESSAO GRAFICA", "Nome_Da_Empresa": "IRISARA COM\u00c9RCIO E SERVI\u00c7OS LTDA.", "CNPJ": "10.376.277/0001-77", "Valor": "1.189,80", "Mes/Ano": "09/2018"}, {"Vereador": " NOEMI NONATO", "Tipo_de_Gasto": "CONTRATA\u00c7AO DE PESSOA JURIDICA", "Nome_Da_Empresa": "MELO ROSA E SOUZA ADVOGADOS ASSOCIADOS", "CNPJ": "06.207.714/0001-51", "Valor": "6.500,00", "Mes/Ano": "09/2018"}, {"Vereador": " NOEMI NONATO", "Tipo_de_Gasto": "CONTRATA\u00c7AO DE PESSOA JURIDICA", "Nome_Da_Empresa": "TECNEGOCIOS SOLU\u00c7OES EM INFORMATICA LTDA- ME", "CNPJ": "11.521.613/0001-90", "Valor": "318,33", "Mes/Ano": "09/2018"}, {"Vereador": " NOEMI NONATO", "Tipo_de_Gasto": "ELABORA\u00c7\u00c3O/MANUTEN\u00c7AO DE SITE/HOSPEDAGEM", "Nome_Da_Empresa": "FABIANA MARIA PEREIRA E SILVA", "CNPJ": "29.378.046/0001-20", "Valor": "5.000,00", "Mes/Ano": "09/2018"}, {"Vereador": " NOEMI NONATO", "Tipo_de_Gasto": "EVENTOS/SEMINARIOS", "Nome_Da_Empresa": "ARTE LU E RO GRAFICA EIRELI", "CNPJ": "18.588.528/0001-99", "Valor": "7.840,00", "Mes/Ano": "09/2018"}, {"Vereador": " NOEMI NONATO", "Tipo_de_Gasto": "EVENTOS/SEMINARIOS", "Nome_Da_Empresa": "FLORICULTURA ROOSEVELT LTDA", "CNPJ": "52.326.162/0001-18", "Valor": "120,00", "Mes/Ano": "09/2018"}, {"Vereador": " NOEMI NONATO", "Tipo_de_Gasto": "INTERMEDIADO - LOCA\u00c7\u00c3O DE VE\u00cdCULOS", "Nome_Da_Empresa": "CAMARA MUNICIPAL DE S\u00c3O PAULO", "CNPJ": "50.176.288/0001-28", "Valor": "2.148,45", "Mes/Ano": "09/2018"}, {"Vereador": " NOEMI NONATO", "Tipo_de_Gasto": "LOCA\u00c7\u00c3O DE MOVEIS E EQUIPAMENTOS", "Nome_Da_Empresa": "K2G SUPRIMENTOS DE IMPRESS\u00c3O E INFORMATICA EIRELLI - ME", "CNPJ": "19.367.661/0001-88", "Valor": "3.095,00", "Mes/Ano": "09/2018"}, {"Vereador": " NOEMI NONATO", "Tipo_de_Gasto": "MATERIAL DE ESCRITORIO E OUTROS MATERIAIS DE CONSUMO", "Nome_Da_Empresa": "CENTER PAPEIS COMERCIAL LTDA.", "CNPJ": "06.226.820/0001-82", "Valor": "304,15", "Mes/Ano": "09/2018"}, {"Vereador": " NOEMI NONATO", "Tipo_de_Gasto": "MATERIAL DE ESCRITORIO E OUTROS MATERIAIS DE CONSUMO", "Nome_Da_Empresa": "K2G SUPRIMENTOS DE IMPRESS\u00c3O E INFORMATICA EIRELLI - ME", "CNPJ": "19.367.661/0001-88", "Valor": "1.260,00", "Mes/Ano": "09/2018"}, {"Vereador": " OTA", "Tipo_de_Gasto": "ASSINATURA DE JORNAIS E REVISTAS", "Nome_Da_Empresa": "S.A O ESTADO DE S. PAULO", "CNPJ": "61.533.949/0001-41", "Valor": "89,90", "Mes/Ano": "09/2018"}, {"Vereador": " OTA", "Tipo_de_Gasto": "COMBUSTIVEL", "Nome_Da_Empresa": "M MARTINEZ COMBUSTIVEIS ME", "CNPJ": "10.785.686/0001-27", "Valor": "595,42", "Mes/Ano": "09/2018"}, {"Vereador": " OTA", "Tipo_de_Gasto": "COMPOSI\u00c7\u00c3O/ARTE/DIAGRAMA\u00c7\u00c3O/PRODU\u00c7\u00c3O/IMPRESSAO GRAFICA", "Nome_Da_Empresa": "IRISARA COM\u00c9RCIO E SERVI\u00c7OS LTDA.", "CNPJ": "10.376.277/0001-77", "Valor": "2.769,00", "Mes/Ano": "09/2018"}, {"Vereador": " OTA", "Tipo_de_Gasto": "CONTRATA\u00c7AO DE PESSOA JURIDICA", "Nome_Da_Empresa": "KLEMP , DE PAULA SOCIEDADE DE ADVOGADOS", "CNPJ": "18.160.749/0001-61", "Valor": "6.000,00", "Mes/Ano": "09/2018"}, {"Vereador": " OTA", "Tipo_de_Gasto": "CONTRATA\u00c7AO DE PESSOA JURIDICA", "Nome_Da_Empresa": "WORK LINE SYSTEM INFORM\u00c1TICA LTDA", "CNPJ": "67.002.329/0001-62", "Valor": "970,00", "Mes/Ano": "09/2018"}, {"Vereador": " OTA", "Tipo_de_Gasto": "INTERMEDIADO - CORREIOS", "Nome_Da_Empresa": "CAMARA MUNICIPAL DE S\u00c3O PAULO", "CNPJ": "50.176.288/0001-28", "Valor": "4.925,82", "Mes/Ano": "09/2018"}, {"Vereador": " OTA", "Tipo_de_Gasto": "INTERMEDIADO - LOCA\u00c7\u00c3O DE VE\u00cdCULOS", "Nome_Da_Empresa": "CAMARA MUNICIPAL DE S\u00c3O PAULO", "CNPJ": "50.176.288/0001-28", "Valor": "2.148,45", "Mes/Ano": "09/2018"}, {"Vereador": " OTA", "Tipo_de_Gasto": "LOCA\u00c7\u00c3O DE MOVEIS E EQUIPAMENTOS", "Nome_Da_Empresa": "K2G SUPRIMENTOS DE IMPRESS\u00c3O E INFORMATICA EIRELLI - ME", "CNPJ": "19.367.661/0001-88", "Valor": "485,00", "Mes/Ano": "09/2018"}, {"Vereador": " OTA", "Tipo_de_Gasto": "MATERIAL DE ESCRITORIO E OUTROS MATERIAIS DE CONSUMO", "Nome_Da_Empresa": "CENTER PAPEIS COMERCIAL LTDA.", "CNPJ": "06.226.820/0001-82", "Valor": "230,35", "Mes/Ano": "09/2018"}, {"Vereador": " OTA", "Tipo_de_Gasto": "MATERIAL DE ESCRITORIO E OUTROS MATERIAIS DE CONSUMO", "Nome_Da_Empresa": "K2G SUPRIMENTOS DE IMPRESS\u00c3O E INFORMATICA EIRELLI - ME", "CNPJ": "19.367.661/0001-88", "Valor": "1.019,00", "Mes/Ano": "09/2018"}, {"Vereador": " OTA", "Tipo_de_Gasto": "REPROGRAFIA (XEROX/ENCADERNA\u00c7\u00c3O)", "Nome_Da_Empresa": "IRISARA COM\u00c9RCIO E SERVI\u00c7OS LTDA.", "CNPJ": "10.376.277/0001-77", "Valor": "1.100,00", "Mes/Ano": "09/2018"}, {"Vereador": " OTA", "Tipo_de_Gasto": "TELEFONE MOVEL", "Nome_Da_Empresa": "NEXTEL TELECOMUNICA\u00c7\u00d5ES LTDA", "CNPJ": "66.970.229/0001-67", "Valor": "191,55", "Mes/Ano": "09/2018"}, {"Vereador": " PATR\u00cdCIA BEZERRA", "Tipo_de_Gasto": "COMBUSTIVEL", "Nome_Da_Empresa": "AUTO POSTO GRANERO LTDA.", "CNPJ": "05.468.615/0001-60", "Valor": "854,35", "Mes/Ano": "09/2018"}, {"Vereador": " PATR\u00cdCIA BEZERRA", "Tipo_de_Gasto": "CONTRATA\u00c7AO DE PESSOA JURIDICA", "Nome_Da_Empresa": "PANGEA COMUNICA\u00c7\u00c3O BORDLESS 360 LTDA", "CNPJ": "07.256.630/0001-70", "Valor": "5.000,00", "Mes/Ano": "09/2018"}, {"Vereador": " PATR\u00cdCIA BEZERRA", "Tipo_de_Gasto": "EVENTOS/SEMINARIOS", "Nome_Da_Empresa": "VISUAL ARTE COPIADORA EIRELLI - ME", "CNPJ": "13.058.505/0001-59", "Valor": "1.583,00", "Mes/Ano": "09/2018"}, {"Vereador": " PATR\u00cdCIA BEZERRA", "Tipo_de_Gasto": "INTERMEDIADO - CORREIOS", "Nome_Da_Empresa": "CAMARA MUNICIPAL DE S\u00c3O PAULO", "CNPJ": "50.176.288/0001-28", "Valor": "9,89", "Mes/Ano": "09/2018"}, {"Vereador": " PATR\u00cdCIA BEZERRA", "Tipo_de_Gasto": "INTERMEDIADO - LOCA\u00c7\u00c3O DE VE\u00cdCULOS", "Nome_Da_Empresa": "CAMARA MUNICIPAL DE S\u00c3O PAULO", "CNPJ": "50.176.288/0001-28", "Valor": "2.148,45", "Mes/Ano": "09/2018"}, {"Vereador": " PATR\u00cdCIA BEZERRA", "Tipo_de_Gasto": "MATERIAL DE ESCRITORIO E OUTROS MATERIAIS DE CONSUMO", "Nome_Da_Empresa": "CENTER PAPEIS COMERCIAL LTDA.", "CNPJ": "06.226.820/0001-82", "Valor": "1.013,45", "Mes/Ano": "09/2018"}, {"Vereador": " PAULO FRANGE", "Tipo_de_Gasto": "COMPOSI\u00c7\u00c3O/ARTE/DIAGRAMA\u00c7\u00c3O/PRODU\u00c7\u00c3O/IMPRESSAO GRAFICA", "Nome_Da_Empresa": "COPYSUL SERV DE FOTOC E COM DE ART DE PAPELARIA LTDA-ME", "CNPJ": "14.625.680/0001-43", "Valor": "7.850,00", "Mes/Ano": "09/2018"}, {"Vereador": " PAULO FRANGE", "Tipo_de_Gasto": "INTERMEDIADO - CORREIOS", "Nome_Da_Empresa": "CAMARA MUNICIPAL DE S\u00c3O PAULO", "CNPJ": "50.176.288/0001-28", "Valor": "1.428,45", "Mes/Ano": "09/2018"}, {"Vereador": " PAULO FRANGE", "Tipo_de_Gasto": "INTERMEDIADO - LOCA\u00c7\u00c3O DE VE\u00cdCULOS", "Nome_Da_Empresa": "CAMARA MUNICIPAL DE S\u00c3O PAULO", "CNPJ": "50.176.288/0001-28", "Valor": "2.148,45", "Mes/Ano": "09/2018"}, {"Vereador": " PAULO FRANGE", "Tipo_de_Gasto": "LOCA\u00c7\u00c3O DE MOVEIS E EQUIPAMENTOS", "Nome_Da_Empresa": "FMJ COM\u00c9RCIO E ASSISTENCIA T\u00c9CNICA EM COPIADORAS LTDA ME", "CNPJ": "07.915.380/0001-33", "Valor": "600,00", "Mes/Ano": "09/2018"}, {"Vereador": " PAULO FRANGE", "Tipo_de_Gasto": "MATERIAL DE ESCRITORIO E OUTROS MATERIAIS DE CONSUMO", "Nome_Da_Empresa": "ESPACIAL SUPRIMENTOS DE ESCRITORIO E INFORMATICA LTDA.", "CNPJ": "53.700.159/0001-85", "Valor": "306,08", "Mes/Ano": "09/2018"}, {"Vereador": " QUITO FORMIGA", "Tipo_de_Gasto": "COMPOSI\u00c7\u00c3O/ARTE/DIAGRAMA\u00c7\u00c3O/PRODU\u00c7\u00c3O/IMPRESSAO GRAFICA", "Nome_Da_Empresa": "JC PRINT GRAFICA E EDITORA LTDA", "CNPJ": "02.407.269/0001-12", "Valor": "5.250,00", "Mes/Ano": "09/2018"}, {"Vereador": " QUITO FORMIGA", "Tipo_de_Gasto": "CONTRATA\u00c7AO DE PESSOA JURIDICA", "Nome_Da_Empresa": "L C P PORTELLA JUNIOR - PUBLICIDADE", "CNPJ": "30.704.930/0001-97", "Valor": "7.500,00", "Mes/Ano": "09/2018"}, {"Vereador": " QUITO FORMIGA", "Tipo_de_Gasto": "ELABORA\u00c7\u00c3O/MANUTEN\u00c7AO DE SITE/HOSPEDAGEM", "Nome_Da_Empresa": "TASK AGENCIA DE TEXTOS LTDA - ME", "CNPJ": "15.384.212/0001-97", "Valor": "7.400,00", "Mes/Ano": "09/2018"}, {"Vereador": " QUITO FORMIGA", "Tipo_de_Gasto": "INTERMEDIADO - LOCA\u00c7\u00c3O DE VE\u00cdCULOS", "Nome_Da_Empresa": "CAMARA MUNICIPAL DE S\u00c3O PAULO", "CNPJ": "50.176.288/0001-28", "Valor": "2.148,45", "Mes/Ano": "09/2018"}, {"Vereador": " QUITO FORMIGA", "Tipo_de_Gasto": "MATERIAL DE ESCRITORIO E OUTROS MATERIAIS DE CONSUMO", "Nome_Da_Empresa": "PAPELARIA OSAKA LTDA", "CNPJ": "43.338.805/0001-52", "Valor": "2.617,00", "Mes/Ano": "09/2018"}, {"Vereador": " REIS", "Tipo_de_Gasto": "COMBUSTIVEL", "Nome_Da_Empresa": "POSTO DE SERVI\u00c7OS MARACAN\u00c3 LTDA", "CNPJ": "62.413.612/0001-63", "Valor": "200,00", "Mes/Ano": "09/2018"}, {"Vereador": " REIS", "Tipo_de_Gasto": "CONTRATA\u00c7AO DE PESSOA JURIDICA", "Nome_Da_Empresa": "ARCHANJO SOCIEDADE INDIVIDUAL DE ADVOCACIA", "CNPJ": "21.599.946/0001-96", "Valor": "8.000,00", "Mes/Ano": "09/2018"}, {"Vereador": " REIS", "Tipo_de_Gasto": "ELABORA\u00c7\u00c3O/MANUTEN\u00c7AO DE SITE/HOSPEDAGEM", "Nome_Da_Empresa": "KILOGRAMA PUBLICIDADE, GR\u00c1FICA E EDITORA LTDA ME", "CNPJ": "22.465.682/0001-40", "Valor": "5.000,00", "Mes/Ano": "09/2018"}, {"Vereador": " REIS", "Tipo_de_Gasto": "INTERMEDIADO - LOCA\u00c7\u00c3O DE VE\u00cdCULOS", "Nome_Da_Empresa": "CAMARA MUNICIPAL DE S\u00c3O PAULO", "CNPJ": "50.176.288/0001-28", "Valor": "2.148,45", "Mes/Ano": "09/2018"}, {"Vereador": " REIS", "Tipo_de_Gasto": "MATERIAL DE ESCRITORIO E OUTROS MATERIAIS DE CONSUMO", "Nome_Da_Empresa": "CENTER PAPEIS COMERCIAL LTDA.", "CNPJ": "06.226.820/0001-82", "Valor": "814,90", "Mes/Ano": "09/2018"}, {"Vereador": " RICARDO NUNES", "Tipo_de_Gasto": "CONTRATA\u00c7AO DE PESSOA JURIDICA", "Nome_Da_Empresa": "M8K AGENCIA LTDA", "CNPJ": "04.368.514/0001-55", "Valor": "2.990,00", "Mes/Ano": "09/2018"}, {"Vereador": " RICARDO NUNES", "Tipo_de_Gasto": "CONTRATA\u00c7AO DE PESSOA JURIDICA", "Nome_Da_Empresa": "FRANQUEIRA E MILANI SOCIEDADE DE ADVOGADOS", "CNPJ": "07.749.313/0001-96", "Valor": "5.000,00", "Mes/Ano": "09/2018"}, {"Vereador": " RICARDO NUNES", "Tipo_de_Gasto": "INTERMEDIADO - CORREIOS", "Nome_Da_Empresa": "CAMARA MUNICIPAL DE S\u00c3O PAULO", "CNPJ": "50.176.288/0001-28", "Valor": "25,05", "Mes/Ano": "09/2018"}, {"Vereador": " RICARDO NUNES", "Tipo_de_Gasto": "MATERIAL DE ESCRITORIO E OUTROS MATERIAIS DE CONSUMO", "Nome_Da_Empresa": "CENTER PAPEIS COMERCIAL LTDA.", "CNPJ": "06.226.820/0001-82", "Valor": "741,20", "Mes/Ano": "09/2018"}, {"Vereador": " RICARDO TEIXEIRA", "Tipo_de_Gasto": "COMPOSI\u00c7\u00c3O/ARTE/DIAGRAMA\u00c7\u00c3O/PRODU\u00c7\u00c3O/IMPRESSAO GRAFICA", "Nome_Da_Empresa": "IMAGEM DIGITAL C\u00d3PIAS LTDA-EPP", "CNPJ": "05.775.094/0001-94", "Valor": "7.500,00", "Mes/Ano": "09/2018"}, {"Vereador": " RICARDO TEIXEIRA", "Tipo_de_Gasto": "CONTRATA\u00c7AO DE PESSOA JURIDICA", "Nome_Da_Empresa": "FERREIRA BRITTO ADVOGADOS", "CNPJ": "03.968.117/0001-51", "Valor": "4.500,00", "Mes/Ano": "09/2018"}, {"Vereador": " RICARDO TEIXEIRA", "Tipo_de_Gasto": "CONTRATA\u00c7AO DE PESSOA JURIDICA", "Nome_Da_Empresa": "WORK LINE SYSTEM INFORM\u00c1TICA LTDA", "CNPJ": "67.002.329/0001-62", "Valor": "2.166,00", "Mes/Ano": "09/2018"}, {"Vereador": " RICARDO TEIXEIRA", "Tipo_de_Gasto": "ELABORA\u00c7\u00c3O/MANUTEN\u00c7AO DE SITE/HOSPEDAGEM", "Nome_Da_Empresa": "SPT SERVI\u00c7OS EMPRESARIAIS LTDA EPP", "CNPJ": "14.419.909/0001-93", "Valor": "2.852,00", "Mes/Ano": "09/2018"}, {"Vereador": " RICARDO TEIXEIRA", "Tipo_de_Gasto": "INTERMEDIADO - CORREIOS", "Nome_Da_Empresa": "CAMARA MUNICIPAL DE S\u00c3O PAULO", "CNPJ": "50.176.288/0001-28", "Valor": "6.015,13", "Mes/Ano": "09/2018"}, {"Vereador": " RICARDO TEIXEIRA", "Tipo_de_Gasto": "LOCA\u00c7\u00c3O DE MOVEIS E EQUIPAMENTOS", "Nome_Da_Empresa": "FMJ COM\u00c9RCIO E ASSISTENCIA T\u00c9CNICA EM COPIADORAS LTDA ME", "CNPJ": "07.915.380/0001-33", "Valor": "1.800,00", "Mes/Ano": "09/2018"}, {"Vereador": " RICARDO TEIXEIRA", "Tipo_de_Gasto": "MATERIAL DE ESCRITORIO E OUTROS MATERIAIS DE CONSUMO", "Nome_Da_Empresa": "CENTER PAPEIS COMERCIAL LTDA.", "CNPJ": "06.226.820/0001-82", "Valor": "2.217,30", "Mes/Ano": "09/2018"}, {"Vereador": " RINALDI DIGILIO", "Tipo_de_Gasto": "COMBUSTIVEL", "Nome_Da_Empresa": "AUTOPOSTO JUATINDIBA LTDA", "CNPJ": "62.466.370/0001-76", "Valor": "1.631,00", "Mes/Ano": "09/2018"}, {"Vereador": " RINALDI DIGILIO", "Tipo_de_Gasto": "CONTRATA\u00c7AO DE PESSOA JURIDICA", "Nome_Da_Empresa": "TECNEGOCIOS SOLU\u00c7OES EM INFORMATICA LTDA- ME", "CNPJ": "11.521.613/0001-90", "Valor": "249,00", "Mes/Ano": "09/2018"}, {"Vereador": " RINALDI DIGILIO", "Tipo_de_Gasto": "CONTRATA\u00c7AO DE PESSOA JURIDICA", "Nome_Da_Empresa": "LEANDRO SOUZA FERREIRA ME", "CNPJ": "26.554.426/0001-80", "Valor": "7.400,00", "Mes/Ano": "09/2018"}, {"Vereador": " RINALDI DIGILIO", "Tipo_de_Gasto": "INTERMEDIADO - CORREIOS", "Nome_Da_Empresa": "CAMARA MUNICIPAL DE S\u00c3O PAULO", "CNPJ": "50.176.288/0001-28", "Valor": "248,52", "Mes/Ano": "09/2018"}, {"Vereador": " RINALDI DIGILIO", "Tipo_de_Gasto": "INTERMEDIADO - LOCA\u00c7\u00c3O DE VE\u00cdCULOS", "Nome_Da_Empresa": "CAMARA MUNICIPAL DE S\u00c3O PAULO", "CNPJ": "50.176.288/0001-28", "Valor": "2.148,45", "Mes/Ano": "09/2018"}, {"Vereador": " RINALDI DIGILIO", "Tipo_de_Gasto": "LOCA\u00c7\u00c3O DE MOVEIS E EQUIPAMENTOS", "Nome_Da_Empresa": "WAVE INFORMATICA LTDA EPP", "CNPJ": "11.090.241/0001-95", "Valor": "1.361,00", "Mes/Ano": "09/2018"}, {"Vereador": " RINALDI DIGILIO", "Tipo_de_Gasto": "MATERIAL DE ESCRITORIO E OUTROS MATERIAIS DE CONSUMO", "Nome_Da_Empresa": "MICROSUPRI SP INFORMATICA LTDA", "CNPJ": "04.084.001/0001-12", "Valor": "239,90", "Mes/Ano": "09/2018"}, {"Vereador": " RINALDI DIGILIO", "Tipo_de_Gasto": "MATERIAL DE ESCRITORIO E OUTROS MATERIAIS DE CONSUMO", "Nome_Da_Empresa": "PAPELARIA E BAZAR POLGRYMAS LTDA", "CNPJ": "43.899.665/0001-91", "Valor": "186,90", "Mes/Ano": "09/2018"}, {"Vereador": " RINALDI DIGILIO", "Tipo_de_Gasto": "TELEFONE FIXO", "Nome_Da_Empresa": "TELEFONICA BRASIL S/A", "CNPJ": "02.558.157/0001-62", "Valor": "157,75", "Mes/Ano": "09/2018"}, {"Vereador": " RINALDI DIGILIO", "Tipo_de_Gasto": "TELEFONE MOVEL", "Nome_Da_Empresa": "TELEFONICA BRASIL S/A", "CNPJ": "02.558.157/0001-62", "Valor": "1.007,46", "Mes/Ano": "09/2018"}, {"Vereador": " RODRIGO GOULART", "Tipo_de_Gasto": "ASSINATURA DE JORNAIS E REVISTAS", "Nome_Da_Empresa": "S.A O ESTADO DE S. PAULO", "CNPJ": "61.533.949/0001-41", "Valor": "115,90", "Mes/Ano": "09/2018"}, {"Vereador": " RODRIGO GOULART", "Tipo_de_Gasto": "COMBUSTIVEL", "Nome_Da_Empresa": "AUTO POSTO PORTAL DE INTERLAGOS LTDA", "CNPJ": "10.203.913/0001-69", "Valor": "431,17", "Mes/Ano": "09/2018"}, {"Vereador": " RODRIGO GOULART", "Tipo_de_Gasto": "CONTRATA\u00c7AO DE PESSOA JURIDICA", "Nome_Da_Empresa": "SUGGESTIVA COMUNICA\u00c7\u00c3O SOCIEDADE SIMPLES LTDA", "CNPJ": "07.287.608/0001-98", "Valor": "2.000,00", "Mes/Ano": "09/2018"}, {"Vereador": " RODRIGO GOULART", "Tipo_de_Gasto": "CONTRATA\u00c7AO DE PESSOA JURIDICA", "Nome_Da_Empresa": "INOUTNET INFORMATICA LTDA ME", "CNPJ": "09.531.721/0001-00", "Valor": "750,00", "Mes/Ano": "09/2018"}, {"Vereador": " RODRIGO GOULART", "Tipo_de_Gasto": "CONTRATA\u00c7AO DE PESSOA JURIDICA", "Nome_Da_Empresa": "TECNEGOCIOS SOLU\u00c7OES EM INFORMATICA LTDA- ME", "CNPJ": "11.521.613/0001-90", "Valor": "750,00", "Mes/Ano": "09/2018"}, {"Vereador": " RODRIGO GOULART", "Tipo_de_Gasto": "INTERMEDIADO - CORREIOS", "Nome_Da_Empresa": "CAMARA MUNICIPAL DE S\u00c3O PAULO", "CNPJ": "50.176.288/0001-28", "Valor": "42,55", "Mes/Ano": "09/2018"}, {"Vereador": " RODRIGO GOULART", "Tipo_de_Gasto": "LOCA\u00c7\u00c3O DE MOVEIS E EQUIPAMENTOS", "Nome_Da_Empresa": "GLOBALNESS COMERCIAL LTDA", "CNPJ": "10.848.194/0001-33", "Valor": "850,00", "Mes/Ano": "09/2018"}, {"Vereador": " RODRIGO GOULART", "Tipo_de_Gasto": "LOCA\u00c7\u00c3O DE VE\u00cdCULOS", "Nome_Da_Empresa": "NEVADA RENT A CAR LTDA", "CNPJ": "58.488.099/0001-00", "Valor": "2.148,45", "Mes/Ano": "09/2018"}, {"Vereador": " RODRIGO GOULART", "Tipo_de_Gasto": "MATERIAL DE ESCRITORIO E OUTROS MATERIAIS DE CONSUMO", "Nome_Da_Empresa": "CENTER PAPEIS COMERCIAL LTDA.", "CNPJ": "06.226.820/0001-82", "Valor": "442,75", "Mes/Ano": "09/2018"}, {"Vereador": " RODRIGO GOULART", "Tipo_de_Gasto": "TELEFONE FIXO", "Nome_Da_Empresa": "CLARO S.A.", "CNPJ": "40.432.544/0001-47", "Valor": "331,65", "Mes/Ano": "09/2018"}, {"Vereador": " RODRIGO GOULART", "Tipo_de_Gasto": "TELEFONE MOVEL", "Nome_Da_Empresa": "TELEFONICA BRASIL S/A", "CNPJ": "02.558.157/0001-62", "Valor": "276,89", "Mes/Ano": "09/2018"}, {"Vereador": " RUTE COSTA", "Tipo_de_Gasto": "ASSINATURA DE JORNAIS E REVISTAS", "Nome_Da_Empresa": "S.A O ESTADO DE S. PAULO", "CNPJ": "61.533.949/0001-41", "Valor": "115,90", "Mes/Ano": "09/2018"}, {"Vereador": " RUTE COSTA", "Tipo_de_Gasto": "COMBUSTIVEL", "Nome_Da_Empresa": "AUTO POSTO TUPI LTDA.", "CNPJ": "63.045.884/0001-10", "Valor": "853,70", "Mes/Ano": "09/2018"}, {"Vereador": " RUTE COSTA", "Tipo_de_Gasto": "COMPOSI\u00c7\u00c3O/ARTE/DIAGRAMA\u00c7\u00c3O/PRODU\u00c7\u00c3O/IMPRESSAO GRAFICA", "Nome_Da_Empresa": "LIBERALINA FREIRE MOURA ME", "CNPJ": "25.217.978/0001-30", "Valor": "7.200,00", "Mes/Ano": "09/2018"}, {"Vereador": " RUTE COSTA", "Tipo_de_Gasto": "CONTRATA\u00c7AO DE PESSOA JURIDICA", "Nome_Da_Empresa": "SOLARYS SOLU\u00c7\u00d5ES DIGITAIS LTDA-ME", "CNPJ": "08.648.207/0001-89", "Valor": "715,00", "Mes/Ano": "09/2018"}, {"Vereador": " RUTE COSTA", "Tipo_de_Gasto": "INTERMEDIADO - CORREIOS", "Nome_Da_Empresa": "CAMARA MUNICIPAL DE S\u00c3O PAULO", "CNPJ": "50.176.288/0001-28", "Valor": "1.631,35", "Mes/Ano": "09/2018"}, {"Vereador": " RUTE COSTA", "Tipo_de_Gasto": "INTERMEDIADO - LOCA\u00c7\u00c3O DE VE\u00cdCULOS", "Nome_Da_Empresa": "CAMARA MUNICIPAL DE S\u00c3O PAULO", "CNPJ": "50.176.288/0001-28", "Valor": "2.148,45", "Mes/Ano": "09/2018"}, {"Vereador": " RUTE COSTA", "Tipo_de_Gasto": "LOCA\u00c7\u00c3O DE MOVEIS E EQUIPAMENTOS", "Nome_Da_Empresa": "ATTBRASIL TECNOLOGIA LOCA\u00c7\u00c3O E SOLU\u00c7\u00d5ES EM INFORMATICA LTDA EPP", "CNPJ": "22.392.165/0001-99", "Valor": "1.775,00", "Mes/Ano": "09/2018"}, {"Vereador": " RUTE COSTA", "Tipo_de_Gasto": "MATERIAL DE ESCRITORIO E OUTROS MATERIAIS DE CONSUMO", "Nome_Da_Empresa": "KALUNGA COM. E IND. GRAFICA LTDA", "CNPJ": "43.283.811/0101-12", "Valor": "398,20", "Mes/Ano": "09/2018"}, {"Vereador": " RUTE COSTA", "Tipo_de_Gasto": "MATERIAL DE ESCRITORIO E OUTROS MATERIAIS DE CONSUMO", "Nome_Da_Empresa": "KALUNGA COM. E IND. GR\u00c1FICA LTDA", "CNPJ": "43.283.811/0177-10", "Valor": "20,00", "Mes/Ano": "09/2018"}, {"Vereador": " RUTE COSTA", "Tipo_de_Gasto": "TELEFONE FIXO", "Nome_Da_Empresa": "TELEFONICA BRASIL S/A", "CNPJ": "02.558.157/0001-62", "Valor": "171,15", "Mes/Ano": "09/2018"}, {"Vereador": " S\u00c2MIA BOMFIM", "Tipo_de_Gasto": "MATERIAL DE ESCRITORIO E OUTROS MATERIAIS DE CONSUMO", "Nome_Da_Empresa": "GLOBAL ACTION COM. SERV. DE EQUIP.DE INFORMATICA LTDA.", "CNPJ": "11.900.316/0001-56", "Valor": "1.237,70", "Mes/Ano": "09/2018"}, {"Vereador": " SANDRA TADEU", "Tipo_de_Gasto": "CONTRATA\u00c7AO DE PESSOA JURIDICA", "Nome_Da_Empresa": "SISNETTI INTEGRADORA DE SOLU\u00c7\u00d5ES LTDA. ME", "CNPJ": "01.319.851/0001-64", "Valor": "622,00", "Mes/Ano": "09/2018"}, {"Vereador": " SANDRA TADEU", "Tipo_de_Gasto": "INTERMEDIADO - CORREIOS", "Nome_Da_Empresa": "CAMARA MUNICIPAL DE S\u00c3O PAULO", "CNPJ": "50.176.288/0001-28", "Valor": "1.329,02", "Mes/Ano": "09/2018"}, {"Vereador": " SANDRA TADEU", "Tipo_de_Gasto": "INTERMEDIADO - LOCA\u00c7\u00c3O DE VE\u00cdCULOS", "Nome_Da_Empresa": "CAMARA MUNICIPAL DE S\u00c3O PAULO", "CNPJ": "50.176.288/0001-28", "Valor": "2.148,45", "Mes/Ano": "09/2018"}, {"Vereador": " SANDRA TADEU", "Tipo_de_Gasto": "INTERMEDIADO - REPROGRAFIA (XEROX/ENCADERNA\u00c7\u00c3O)", "Nome_Da_Empresa": "CAMARA MUNICIPAL DE S\u00c3O PAULO", "CNPJ": "50.176.288/0001-28", "Valor": "63,00", "Mes/Ano": "09/2018"}, {"Vereador": " SANDRA TADEU", "Tipo_de_Gasto": "MATERIAL DE ESCRITORIO E OUTROS MATERIAIS DE CONSUMO", "Nome_Da_Empresa": "K2G SUPRIMENTOS DE IMPRESS\u00c3O E INFORMATICA EIRELLI - ME", "CNPJ": "19.367.661/0001-88", "Valor": "1.606,00", "Mes/Ano": "09/2018"}, {"Vereador": " SANDRA TADEU", "Tipo_de_Gasto": "TELEFONE FIXO", "Nome_Da_Empresa": "TELEFONICA BRASIL S/A", "CNPJ": "02.558.157/0001-62", "Valor": "388,04", "Mes/Ano": "09/2018"}, {"Vereador": " SANDRA TADEU", "Tipo_de_Gasto": "TELEFONE MOVEL", "Nome_Da_Empresa": "TELEFONICA BRASIL S/A", "CNPJ": "02.558.157/0001-62", "Valor": "589,99", "Mes/Ano": "09/2018"}, {"Vereador": " SENIVAL MOURA", "Tipo_de_Gasto": "COMPOSI\u00c7\u00c3O/ARTE/DIAGRAMA\u00c7\u00c3O/PRODU\u00c7\u00c3O/IMPRESSAO GRAFICA", "Nome_Da_Empresa": "J. C. DE ARAUJO GRAFICAS ME", "CNPJ": "13.623.472/0001-42", "Valor": "7.500,00", "Mes/Ano": "09/2018"}, {"Vereador": " SENIVAL MOURA", "Tipo_de_Gasto": "ELABORA\u00c7\u00c3O/MANUTEN\u00c7AO DE SITE/HOSPEDAGEM", "Nome_Da_Empresa": "PROSPECT COMUNICA\u00c7\u00c3O E MARKETING LTDA-ME", "CNPJ": "26.885.016/0001-12", "Valor": "4.000,00", "Mes/Ano": "09/2018"}, {"Vereador": " SENIVAL MOURA", "Tipo_de_Gasto": "INTERMEDIADO - CORREIOS", "Nome_Da_Empresa": "CAMARA MUNICIPAL DE S\u00c3O PAULO", "CNPJ": "50.176.288/0001-28", "Valor": "17,29", "Mes/Ano": "09/2018"}, {"Vereador": " SENIVAL MOURA", "Tipo_de_Gasto": "INTERMEDIADO - LOCA\u00c7\u00c3O DE VE\u00cdCULOS", "Nome_Da_Empresa": "CAMARA MUNICIPAL DE S\u00c3O PAULO", "CNPJ": "50.176.288/0001-28", "Valor": "2.148,45", "Mes/Ano": "09/2018"}, {"Vereador": " SENIVAL MOURA", "Tipo_de_Gasto": "LOCA\u00c7\u00c3O DE MOVEIS E EQUIPAMENTOS", "Nome_Da_Empresa": "SINALL COM E SERV DE M\u00c1QUINAS LTDA", "CNPJ": "69.064.053/0001-72", "Valor": "1.256,54", "Mes/Ano": "09/2018"}, {"Vereador": " SENIVAL MOURA", "Tipo_de_Gasto": "REPROGRAFIA (XEROX/ENCADERNA\u00c7\u00c3O)", "Nome_Da_Empresa": "TOP MANUSEIO SOLU\u00c7\u00d5ES LOGISTICAS GRAFICAS E POSTAIS LTDA-ME", "CNPJ": "23.826.867/0001-04", "Valor": "7.840,00", "Mes/Ano": "09/2018"}, {"Vereador": " SONINHA", "Tipo_de_Gasto": "COMBUSTIVEL", "Nome_Da_Empresa": "CARLOS ALBERTO PAPACIDERO", "CNPJ": "08.316.625/0001-79", "Valor": "183,01", "Mes/Ano": "09/2018"}, {"Vereador": " SONINHA", "Tipo_de_Gasto": "COMPOSI\u00c7\u00c3O/ARTE/DIAGRAMA\u00c7\u00c3O/PRODU\u00c7\u00c3O/IMPRESSAO GRAFICA", "Nome_Da_Empresa": "K9 INDUSTRIA GRAFICA E SERVI\u00c7OS DE IMPRESSAO LTDA ME", "CNPJ": "09.419.299/0001-98", "Valor": "4.050,00", "Mes/Ano": "09/2018"}, {"Vereador": " SONINHA", "Tipo_de_Gasto": "CONTRATA\u00c7AO DE PESSOA JURIDICA", "Nome_Da_Empresa": "BADAR\u00d3 COMUNICA\u00c7\u00c3O E DESIGN LTDA.", "CNPJ": "17.948.425/0001-20", "Valor": "200,00", "Mes/Ano": "09/2018"}, {"Vereador": " SONINHA", "Tipo_de_Gasto": "CONTRATA\u00c7AO DE PESSOA JURIDICA", "Nome_Da_Empresa": "VINICIUS DOMINICHELLI", "CNPJ": "28.846.874/0001-83", "Valor": "6.750,00", "Mes/Ano": "09/2018"}, {"Vereador": " SONINHA", "Tipo_de_Gasto": "ELABORA\u00c7\u00c3O/MANUTEN\u00c7AO DE SITE/HOSPEDAGEM", "Nome_Da_Empresa": "DEMOCRACIA DIGITAL BRASIL COMUNICA\u00c7\u00c3O LTDA", "CNPJ": "11.998.257/0001-09", "Valor": "6.000,00", "Mes/Ano": "09/2018"}, {"Vereador": " SONINHA", "Tipo_de_Gasto": "LOCA\u00c7\u00c3O DE MOVEIS E EQUIPAMENTOS", "Nome_Da_Empresa": "BRUNO ARAUJO COSTA 28880881850", "CNPJ": "13.913.679/0001-51", "Valor": "6.010,00", "Mes/Ano": "09/2018"}, {"Vereador": " SONINHA", "Tipo_de_Gasto": "TELEFONE FIXO", "Nome_Da_Empresa": "TELEFONICA BRASIL S/A", "CNPJ": "02.558.157/0001-62", "Valor": "127,01", "Mes/Ano": "09/2018"}, {"Vereador": " SONINHA", "Tipo_de_Gasto": "TELEFONE MOVEL", "Nome_Da_Empresa": "CLARO S.A.", "CNPJ": "40.432.544/0001-47", "Valor": "433,68", "Mes/Ano": "09/2018"}, {"Vereador": " SOUZA SANTOS", "Tipo_de_Gasto": "COMBUSTIVEL", "Nome_Da_Empresa": "AUTO POSTO GRANERO LTDA.", "CNPJ": "05.468.615/0001-60", "Valor": "2.702,81", "Mes/Ano": "09/2018"}, {"Vereador": " SOUZA SANTOS", "Tipo_de_Gasto": "CONTRATA\u00c7AO DE PESSOA JURIDICA", "Nome_Da_Empresa": "OLIVEIRA E ALVES SOUZA SOCIEDADE DE ADVOGADOS", "CNPJ": "27.325.829/0001-10", "Valor": "7.000,00", "Mes/Ano": "09/2018"}, {"Vereador": " SOUZA SANTOS", "Tipo_de_Gasto": "CONTRATA\u00c7AO DE PESSOA JURIDICA", "Nome_Da_Empresa": "WORK LINE SYSTEM INFORM\u00c1TICA LTDA", "CNPJ": "67.002.329/0001-62", "Valor": "970,00", "Mes/Ano": "09/2018"}, {"Vereador": " SOUZA SANTOS", "Tipo_de_Gasto": "INTERMEDIADO - CORREIOS", "Nome_Da_Empresa": "CAMARA MUNICIPAL DE S\u00c3O PAULO", "CNPJ": "50.176.288/0001-28", "Valor": "1.879,51", "Mes/Ano": "09/2018"}, {"Vereador": " SOUZA SANTOS", "Tipo_de_Gasto": "INTERMEDIADO - LOCA\u00c7\u00c3O DE VE\u00cdCULOS", "Nome_Da_Empresa": "CAMARA MUNICIPAL DE S\u00c3O PAULO", "CNPJ": "50.176.288/0001-28", "Valor": "2.148,45", "Mes/Ano": "09/2018"}, {"Vereador": " SOUZA SANTOS", "Tipo_de_Gasto": "LOCA\u00c7\u00c3O DE MOVEIS E EQUIPAMENTOS", "Nome_Da_Empresa": "SINALL COM E SERV DE M\u00c1QUINAS LTDA", "CNPJ": "69.064.053/0001-72", "Valor": "302,62", "Mes/Ano": "09/2018"}, {"Vereador": " SOUZA SANTOS", "Tipo_de_Gasto": "MATERIAL DE ESCRITORIO E OUTROS MATERIAIS DE CONSUMO", "Nome_Da_Empresa": "CENTER PAPEIS COMERCIAL LTDA.", "CNPJ": "06.226.820/0001-82", "Valor": "571,25", "Mes/Ano": "09/2018"}, {"Vereador": " SOUZA SANTOS", "Tipo_de_Gasto": "TELEFONE FIXO", "Nome_Da_Empresa": "TELEFONICA BRASIL S/A", "CNPJ": "02.558.157/0001-62", "Valor": "346,97", "Mes/Ano": "09/2018"}, {"Vereador": " TONINHO PAIVA", "Tipo_de_Gasto": "COMBUSTIVEL", "Nome_Da_Empresa": "CENTRO AUTOMOTIVO FENIX LTDA", "CNPJ": "00.533.599/0001-29", "Valor": "1.166,49", "Mes/Ano": "09/2018"}, {"Vereador": " TONINHO PAIVA", "Tipo_de_Gasto": "CONTRATA\u00c7AO DE PESSOA JURIDICA", "Nome_Da_Empresa": "SPT SERVI\u00c7OS EMPRESARIAIS LTDA EPP", "CNPJ": "14.419.909/0001-93", "Valor": "4.600,00", "Mes/Ano": "09/2018"}, {"Vereador": " TONINHO PAIVA", "Tipo_de_Gasto": "CONTRATA\u00c7AO DE PESSOA JURIDICA", "Nome_Da_Empresa": "MOBYWAY DESENVOLVIMENTO DE APLICATIVOS LTDA", "CNPJ": "23.114.094/0001-25", "Valor": "300,00", "Mes/Ano": "09/2018"}, {"Vereador": " TONINHO PAIVA", "Tipo_de_Gasto": "CONTRATA\u00c7AO DE PESSOA JURIDICA", "Nome_Da_Empresa": "WORK LINE SYSTEM INFORM\u00c1TICA LTDA", "CNPJ": "67.002.329/0001-62", "Valor": "970,00", "Mes/Ano": "09/2018"}, {"Vereador": " TONINHO PAIVA", "Tipo_de_Gasto": "INTERMEDIADO - CORREIOS", "Nome_Da_Empresa": "CAMARA MUNICIPAL DE S\u00c3O PAULO", "CNPJ": "50.176.288/0001-28", "Valor": "4.771,21", "Mes/Ano": "09/2018"}, {"Vereador": " TONINHO PAIVA", "Tipo_de_Gasto": "INTERMEDIADO - LOCA\u00c7\u00c3O DE VE\u00cdCULOS", "Nome_Da_Empresa": "CAMARA MUNICIPAL DE S\u00c3O PAULO", "CNPJ": "50.176.288/0001-28", "Valor": "2.148,45", "Mes/Ano": "09/2018"}, {"Vereador": " TONINHO PAIVA", "Tipo_de_Gasto": "LOCA\u00c7\u00c3O DE MOVEIS E EQUIPAMENTOS", "Nome_Da_Empresa": "SOLUTION AUTOMA\u00c7\u00c3O EMPRESARIAL LTDA", "CNPJ": "39.006.762/0001-30", "Valor": "428,68", "Mes/Ano": "09/2018"}, {"Vereador": " TONINHO PAIVA", "Tipo_de_Gasto": "TELEFONE FIXO", "Nome_Da_Empresa": "TELEFONICA BRASIL S/A", "CNPJ": "02.558.157/0001-62", "Valor": "226,97", "Mes/Ano": "09/2018"}, {"Vereador": " TONINHO PAIVA", "Tipo_de_Gasto": "TELEFONE MOVEL", "Nome_Da_Empresa": "TELEFONICA BRASIL S/A", "CNPJ": "02.558.157/0001-62", "Valor": "504,98", "Mes/Ano": "09/2018"}, {"Vereador": " TONINHO VESPOLI", "Tipo_de_Gasto": "COMBUSTIVEL", "Nome_Da_Empresa": "AUTO POSTO GUAIRACA LTDA", "CNPJ": "43.234.889/0001-84", "Valor": "846,50", "Mes/Ano": "09/2018"}, {"Vereador": " TONINHO VESPOLI", "Tipo_de_Gasto": "COMPOSI\u00c7\u00c3O/ARTE/DIAGRAMA\u00c7\u00c3O/PRODU\u00c7\u00c3O/IMPRESSAO GRAFICA", "Nome_Da_Empresa": "FORMA CERTA GRAFICA  DIGITAL LTDA", "CNPJ": "07.691.829/0001-27", "Valor": "6.490,00", "Mes/Ano": "09/2018"}, {"Vereador": " TONINHO VESPOLI", "Tipo_de_Gasto": "CONTRATA\u00c7AO DE PESSOA JURIDICA", "Nome_Da_Empresa": "JULIANA RISOLI GHIZZI", "CNPJ": "29.666.296/0001-66", "Valor": "3.500,00", "Mes/Ano": "09/2018"}, {"Vereador": " TONINHO VESPOLI", "Tipo_de_Gasto": "CONTRATA\u00c7AO DE PESSOA JURIDICA", "Nome_Da_Empresa": "ANDRE FEITOSA ALCANTARA", "CNPJ": "29.992.029/0001-89", "Valor": "2.800,00", "Mes/Ano": "09/2018"}, {"Vereador": " TONINHO VESPOLI", "Tipo_de_Gasto": "LOCA\u00c7\u00c3O DE MOVEIS E EQUIPAMENTOS", "Nome_Da_Empresa": "CONVEX LOCA\u00c7\u00c3O DE EQUIPAMENTOS PARA EVENTOS LTDA-EPP", "CNPJ": "07.066.295/0001-48", "Valor": "260,00", "Mes/Ano": "09/2018"}, {"Vereador": " TONINHO VESPOLI", "Tipo_de_Gasto": "LOCA\u00c7\u00c3O DE MOVEIS E EQUIPAMENTOS", "Nome_Da_Empresa": "KITANI LOCA\u00c7\u00c3O E COM\u00c9RCIO DE EQUIPAMENTOS LTDA", "CNPJ": "49.557.960/0001-46", "Valor": "1.149,44", "Mes/Ano": "09/2018"}, {"Vereador": " TONINHO VESPOLI", "Tipo_de_Gasto": "MATERIAL DE ESCRITORIO E OUTROS MATERIAIS DE CONSUMO", "Nome_Da_Empresa": "CENTER PAPEIS COMERCIAL LTDA.", "CNPJ": "06.226.820/0001-82", "Valor": "487,70", "Mes/Ano": "09/2018"}, {"Vereador": " TONINHO VESPOLI", "Tipo_de_Gasto": "TELEFONE FIXO", "Nome_Da_Empresa": "TELEFONICA BRASIL S/A", "CNPJ": "02.558.157/0001-62", "Valor": "121,59", "Mes/Ano": "09/2018"}, {"Vereador": " TONINHO VESPOLI", "Tipo_de_Gasto": "TELEFONE MOVEL", "Nome_Da_Empresa": "TELEFONICA BRASIL S/A", "CNPJ": "02.558.157/0001-62", "Valor": "489,99", "Mes/Ano": "09/2018"}, {"Vereador": " XEX\u00c9U TRIPOLI", "Tipo_de_Gasto": "INTERMEDIADO - LOCA\u00c7\u00c3O DE VE\u00cdCULOS", "Nome_Da_Empresa": "CAMARA MUNICIPAL DE S\u00c3O PAULO", "CNPJ": "50.176.288/0001-28", "Valor": "2.148,45", "Mes/Ano": "09/2018"}, {"Vereador": " Z\u00c9 TURIN", "Tipo_de_Gasto": "ASSINATURA DE JORNAIS E REVISTAS", "Nome_Da_Empresa": "S.A O ESTADO DE S. PAULO", "CNPJ": "61.533.949/0001-41", "Valor": "69,50", "Mes/Ano": "09/2018"}, {"Vereador": " Z\u00c9 TURIN", "Tipo_de_Gasto": "COMBUSTIVEL", "Nome_Da_Empresa": "AUTO POSTO GRANERO LTDA.", "CNPJ": "05.468.615/0001-60", "Valor": "1.260,43", "Mes/Ano": "09/2018"}, {"Vereador": " Z\u00c9 TURIN", "Tipo_de_Gasto": "COMPOSI\u00c7\u00c3O/ARTE/DIAGRAMA\u00c7\u00c3O/PRODU\u00c7\u00c3O/IMPRESSAO GRAFICA", "Nome_Da_Empresa": "CESAR VIEIRA MENDES ME", "CNPJ": "11.045.359/0001-00", "Valor": "8.000,00", "Mes/Ano": "09/2018"}, {"Vereador": " Z\u00c9 TURIN", "Tipo_de_Gasto": "INTERMEDIADO - CORREIOS", "Nome_Da_Empresa": "CAMARA MUNICIPAL DE S\u00c3O PAULO", "CNPJ": "50.176.288/0001-28", "Valor": "306,59", "Mes/Ano": "09/2018"}, {"Vereador": " Z\u00c9 TURIN", "Tipo_de_Gasto": "INTERMEDIADO - LOCA\u00c7\u00c3O DE VE\u00cdCULOS", "Nome_Da_Empresa": "CAMARA MUNICIPAL DE S\u00c3O PAULO", "CNPJ": "50.176.288/0001-28", "Valor": "2.148,45", "Mes/Ano": "09/2018"}, {"Vereador": " Z\u00c9 TURIN", "Tipo_de_Gasto": "LOCA\u00c7\u00c3O DE MOVEIS E EQUIPAMENTOS", "Nome_Da_Empresa": "BRIX CONSTRU\u00c7\u00d5ES E SERVI\u00c7OS", "CNPJ": "20.337.161/0001-82", "Valor": "500,00", "Mes/Ano": "09/2018"}, {"Vereador": " Z\u00c9 TURIN", "Tipo_de_Gasto": "PROVEDOR DE INTERNET", "Nome_Da_Empresa": "TELEFONICA BRASIL S/A", "CNPJ": "02.558.157/0001-62", "Valor": "149,70", "Mes/Ano": "09/2018"}]